{
  "metadata": {
    "timestamp": "20251203_201353",
    "test_date": "2025-12-03T20:13:53.347356",
    "monitor_width": 1512,
    "monitor_height": 982,
    "total_targets": 12,
    "gap_duration_ms": 200
  },
  "results": {
    "normal_saccade": {
      "total_saccades": 10,
      "valid_saccades": 10,
      "average_latency_ms": 231.2535888671875,
      "average_velocity_deg_per_ms": 0.24512564043806676,
      "average_accuracy_percent": 47.56731427572084,
      "std_latency_ms": 112.58135527308208,
      "std_velocity_deg_per_ms": 0.2204045586494797,
      "std_accuracy_percent": 49.15704893784297
    },
    "antisaccade": {
      "total_trials": 12,
      "error_count": 0,
      "correct_count": 12,
      "error_rate_percent": 0.0
    }
  },
  "normal_saccade_data": [
    {
      "target_index": 1,
      "target_angle_degrees": 23.87231427004509,
      "target_x": 1425,
      "target_y": 491,
      "saccade_latency_ms": 196.914794921875,
      "peak_velocity_deg_per_ms": 0.06454416934721559,
      "peak_velocity_deg_per_s": 64.54416934721559,
      "accuracy_percent": 0.0
    },
    {
      "target_index": 2,
      "target_angle_degrees": 21.329648117997873,
      "target_x": 1346,
      "target_y": 491,
      "saccade_latency_ms": 396.115234375,
      "peak_velocity_deg_per_ms": 0.6345499932227928,
      "peak_velocity_deg_per_s": 634.5499932227929,
      "accuracy_percent": 124.41644712344488
    },
    {
      "target_index": 3,
      "target_angle_degrees": -18.551648037565343,
      "target_x": 249,
      "target_y": 491,
      "saccade_latency_ms": 78.6513671875,
      "peak_velocity_deg_per_ms": 0.0412891009781172,
      "peak_velocity_deg_per_s": 41.2891009781172,
      "accuracy_percent": 2.655677150023538
    },
    {
      "target_index": 4,
      "target_angle_degrees": 23.02744673898088,
      "target_x": 1398,
      "target_y": 491,
      "saccade_latency_ms": 390.437744140625,
      "peak_velocity_deg_per_ms": 0.3291382337093081,
      "peak_velocity_deg_per_s": 329.1382337093081,
      "accuracy_percent": 56.6060580280209
    },
    {
      "target_index": 6,
      "target_angle_degrees": 15.238794652005796,
      "target_x": 1167,
      "target_y": 491,
      "saccade_latency_ms": 78.691162109375,
      "peak_velocity_deg_per_ms": 0.03457811944171914,
      "peak_velocity_deg_per_s": 34.57811944171914,
      "accuracy_percent": 0.0
    },
    {
      "target_index": 7,
      "target_angle_degrees": -16.177785301180197,
      "target_x": 318,
      "target_y": 491,
      "saccade_latency_ms": 229.952880859375,
      "peak_velocity_deg_per_ms": 0.03524126723391995,
      "peak_velocity_deg_per_s": 35.241267233919956,
      "accuracy_percent": 5.856073027876987
    },
    {
      "target_index": 8,
      "target_angle_degrees": -26.57390759415223,
      "target_x": 0,
      "target_y": 491,
      "saccade_latency_ms": 119.853759765625,
      "peak_velocity_deg_per_ms": 0.033114710423941485,
      "peak_velocity_deg_per_s": 33.11471042394148,
      "accuracy_percent": 3.5650869868259023
    },
    {
      "target_index": 9,
      "target_angle_degrees": 11.598405381943593,
      "target_x": 1066,
      "target_y": 491,
      "saccade_latency_ms": 349.60888671875,
      "peak_velocity_deg_per_ms": 0.4618944932581699,
      "peak_velocity_deg_per_s": 461.8944932581699,
      "accuracy_percent": 120.1102356698146
    },
    {
      "target_index": 10,
      "target_angle_degrees": 18.927782825528567,
      "target_x": 1274,
      "target_y": 491,
      "saccade_latency_ms": 239.08203125,
      "peak_velocity_deg_per_ms": 0.310365404567408,
      "peak_velocity_deg_per_s": 310.365404567408,
      "accuracy_percent": 66.58219796937928
    },
    {
      "target_index": 11,
      "target_angle_degrees": -18.51480781991839,
      "target_x": 250,
      "target_y": 491,
      "saccade_latency_ms": 233.22802734375,
      "peak_velocity_deg_per_ms": 0.5065409121980753,
      "peak_velocity_deg_per_s": 506.54091219807526,
      "accuracy_percent": 95.88136680182225
    }
  ],
  "antisaccade_data": [
    {
      "target_index": 0,
      "target_angle_degrees": 9.855819763337607,
      "target_x": 1018,
      "target_y": 491,
      "error": false
    },
    {
      "target_index": 1,
      "target_angle_degrees": 19.799956197802892,
      "target_x": 1300,
      "target_y": 491,
      "error": false
    },
    {
      "target_index": 2,
      "target_angle_degrees": -5.030081065924928,
      "target_x": 623,
      "target_y": 491,
      "error": false
    },
    {
      "target_index": 3,
      "target_angle_degrees": -8.649306849786786,
      "target_x": 527,
      "target_y": 491,
      "error": false
    },
    {
      "target_index": 4,
      "target_angle_degrees": -14.57965066714872,
      "target_x": 363,
      "target_y": 491,
      "error": false
    },
    {
      "target_index": 5,
      "target_angle_degrees": -8.001468252554895,
      "target_x": 544,
      "target_y": 491,
      "error": false
    },
    {
      "target_index": 6,
      "target_angle_degrees": -7.24563663288969,
      "target_x": 564,
      "target_y": 491,
      "error": false
    },
    {
      "target_index": 7,
      "target_angle_degrees": -13.294658765051686,
      "target_x": 399,
      "target_y": 491,
      "error": false
    },
    {
      "target_index": 8,
      "target_angle_degrees": 11.350155644926057,
      "target_x": 1059,
      "target_y": 491,
      "error": false
    },
    {
      "target_index": 9,
      "target_angle_degrees": -7.7306556625013325,
      "target_x": 551,
      "target_y": 491,
      "error": false
    },
    {
      "target_index": 10,
      "target_angle_degrees": -18.63140139423579,
      "target_x": 247,
      "target_y": 491,
      "error": false
    },
    {
      "target_index": 11,
      "target_angle_degrees": -17.831136938922626,
      "target_x": 270,
      "target_y": 491,
      "error": false
    }
  ],
  "gaze_path": [
    [
      1764810785806.7961,
      756,
      453
    ],
    [
      1764810785843.5059,
      768,
      528
    ],
    [
      1764810785887.0088,
      768,
      528
    ],
    [
      1764810785923.282,
      756,
      472
    ],
    [
      1764810785963.9832,
      756,
      491
    ],
    [
      1764810786006.891,
      756,
      528
    ],
    [
      1764810786042.5679,
      756,
      528
    ],
    [
      1764810786076.64,
      756,
      528
    ],
    [
      1764810786113.013,
      756,
      528
    ],
    [
      1764810786148.4978,
      756,
      528
    ],
    [
      1764810786196.084,
      768,
      528
    ],
    [
      1764810786237.2532,
      631,
      397
    ],
    [
      1764810786278.177,
      520,
      359
    ],
    [
      1764810786319.968,
      520,
      359
    ],
    [
      1764810786355.242,
      520,
      359
    ],
    [
      1764810786398.057,
      520,
      359
    ],
    [
      1764810786437.7651,
      520,
      359
    ],
    [
      1764810786473.065,
      520,
      435
    ],
    [
      1764810786508.852,
      520,
      341
    ],
    [
      1764810786551.432,
      520,
      397
    ],
    [
      1764810786598.499,
      532,
      378
    ],
    [
      1764810786634.2112,
      507,
      341
    ],
    [
      1764810786668.308,
      458,
      472
    ],
    [
      1764810786711.061,
      445,
      453
    ],
    [
      1764810786747.003,
      445,
      453
    ],
    [
      1764810786787.967,
      445,
      472
    ],
    [
      1764810786828.9258,
      433,
      397
    ],
    [
      1764810786870.386,
      818,
      397
    ],
    [
      1764810786906.1492,
      968,
      397
    ],
    [
      1764810786941.52,
      968,
      378
    ],
    [
      1764810786979.0398,
      981,
      453
    ],
    [
      1764810787021.186,
      968,
      435
    ],
    [
      1764810787061.497,
      981,
      435
    ],
    [
      1764810787100.961,
      981,
      416
    ],
    [
      1764810787136.765,
      968,
      416
    ],
    [
      1764810787170.8647,
      793,
      453
    ],
    [
      1764810787213.5369,
      806,
      416
    ],
    [
      1764810787254.667,
      793,
      435
    ],
    [
      1764810787289.971,
      793,
      416
    ],
    [
      1764810787330.0427,
      781,
      453
    ],
    [
      1764810787384.1091,
      781,
      416
    ],
    [
      1764810787428.575,
      781,
      416
    ],
    [
      1764810787469.8298,
      781,
      453
    ],
    [
      1764810787511.283,
      793,
      453
    ],
    [
      1764810787545.039,
      781,
      397
    ],
    [
      1764810787579.139,
      781,
      416
    ],
    [
      1764810787621.643,
      781,
      397
    ],
    [
      1764810787662.798,
      781,
      435
    ],
    [
      1764810787698.658,
      768,
      397
    ],
    [
      1764810787731.8918,
      768,
      453
    ],
    [
      1764810787781.761,
      619,
      378
    ],
    [
      1764810787823.638,
      470,
      397
    ],
    [
      1764810787858.9282,
      470,
      435
    ],
    [
      1764810787901.28,
      470,
      397
    ],
    [
      1764810787943.3037,
      470,
      453
    ],
    [
      1764810787990.138,
      458,
      453
    ],
    [
      1764810788032.2292,
      458,
      416
    ],
    [
      1764810788066.668,
      458,
      416
    ],
    [
      1764810788102.53,
      458,
      397
    ],
    [
      1764810788138.5842,
      458,
      416
    ],
    [
      1764810788181.033,
      371,
      397
    ],
    [
      1764810788221.072,
      371,
      416
    ],
    [
      1764810788263.218,
      371,
      416
    ],
    [
      1764810788299.25,
      383,
      528
    ],
    [
      1764810788341.301,
      359,
      435
    ],
    [
      1764810788382.5999,
      359,
      416
    ],
    [
      1764810788420.816,
      359,
      416
    ],
    [
      1764810788469.665,
      371,
      509
    ],
    [
      1764810788511.8862,
      371,
      509
    ],
    [
      1764810788547.096,
      371,
      491
    ],
    [
      1764810788589.249,
      359,
      416
    ],
    [
      1764810788631.344,
      371,
      509
    ],
    [
      1764810788667.036,
      396,
      453
    ],
    [
      1764810788707.284,
      843,
      397
    ],
    [
      1764810788749.3298,
      843,
      397
    ],
    [
      1764810788790.993,
      843,
      397
    ],
    [
      1764810788825.8403,
      856,
      416
    ],
    [
      1764810788860.4421,
      856,
      416
    ],
    [
      1764810788897.5562,
      856,
      435
    ],
    [
      1764810788938.4817,
      856,
      472
    ],
    [
      1764810788981.096,
      706,
      435
    ],
    [
      1764810789023.2397,
      706,
      491
    ],
    [
      1764810789059.525,
      706,
      472
    ],
    [
      1764810789094.899,
      706,
      472
    ],
    [
      1764810789131.4548,
      706,
      472
    ],
    [
      1764810789171.322,
      706,
      491
    ],
    [
      1764810789213.519,
      706,
      416
    ],
    [
      1764810789255.048,
      706,
      491
    ],
    [
      1764810789290.956,
      706,
      453
    ],
    [
      1764810789333.3152,
      694,
      435
    ],
    [
      1764810789380.8542,
      669,
      472
    ],
    [
      1764810789422.951,
      656,
      472
    ],
    [
      1764810789457.7588,
      656,
      472
    ],
    [
      1764810789492.58,
      669,
      453
    ],
    [
      1764810789535.717,
      656,
      472
    ],
    [
      1764810789571.019,
      656,
      453
    ],
    [
      1764810789612.268,
      669,
      453
    ],
    [
      1764810789653.47,
      669,
      453
    ],
    [
      1764810789689.214,
      669,
      453
    ],
    [
      1764810789724.777,
      706,
      472
    ],
    [
      1764810789767.3481,
      706,
      509
    ],
    [
      1764810789802.535,
      706,
      472
    ],
    [
      1764810789843.3862,
      706,
      491
    ],
    [
      1764810789885.437,
      706,
      528
    ],
    [
      1764810789927.1592,
      706,
      491
    ],
    [
      1764810789962.031,
      706,
      472
    ],
    [
      1764810790004.948,
      718,
      528
    ],
    [
      1764810790045.549,
      718,
      472
    ],
    [
      1764810790086.988,
      706,
      472
    ],
    [
      1764810790122.281,
      718,
      528
    ],
    [
      1764810790156.513,
      557,
      491
    ],
    [
      1764810790199.7012,
      0,
      453
    ],
    [
      1764810790234.1042,
      0,
      435
    ],
    [
      1764810790268.8599,
      0,
      435
    ],
    [
      1764810790309.142,
      0,
      435
    ],
    [
      1764810790351.5962,
      0,
      453
    ],
    [
      1764810790386.904,
      0,
      435
    ],
    [
      1764810790429.033,
      0,
      435
    ],
    [
      1764810790470.82,
      0,
      435
    ],
    [
      1764810790505.2957,
      0,
      453
    ],
    [
      1764810790545.9849,
      0,
      453
    ],
    [
      1764810790581.093,
      0,
      453
    ],
    [
      1764810790617.071,
      0,
      453
    ],
    [
      1764810790652.114,
      0,
      472
    ],
    [
      1764810790694.6099,
      0,
      435
    ],
    [
      1764810790729.353,
      173,
      491
    ],
    [
      1764810790763.4702,
      607,
      397
    ],
    [
      1764810790805.26,
      644,
      509
    ],
    [
      1764810790846.365,
      644,
      528
    ],
    [
      1764810790881.8628,
      644,
      491
    ],
    [
      1764810790916.094,
      656,
      528
    ],
    [
      1764810790959.439,
      656,
      491
    ],
    [
      1764810790993.487,
      656,
      491
    ],
    [
      1764810791027.853,
      656,
      491
    ],
    [
      1764810791071.049,
      656,
      491
    ],
    [
      1764810791107.0652,
      681,
      491
    ],
    [
      1764810791149.085,
      731,
      528
    ],
    [
      1764810791191.145,
      731,
      528
    ],
    [
      1764810791231.689,
      731,
      528
    ],
    [
      1764810791266.956,
      731,
      509
    ],
    [
      1764810791309.344,
      731,
      509
    ],
    [
      1764810791351.1218,
      731,
      491
    ],
    [
      1764810791387.0398,
      743,
      528
    ],
    [
      1764810791435.3918,
      731,
      472
    ],
    [
      1764810791477.128,
      743,
      528
    ],
    [
      1764810791519.2617,
      743,
      528
    ],
    [
      1764810791555.489,
      743,
      509
    ],
    [
      1764810791597.44,
      743,
      472
    ],
    [
      1764810791639.246,
      743,
      509
    ],
    [
      1764810791679.038,
      743,
      472
    ],
    [
      1764810791713.949,
      756,
      509
    ],
    [
      1764810791756.0679,
      743,
      472
    ],
    [
      1764810791799.1682,
      756,
      509
    ],
    [
      1764810791834.422,
      756,
      509
    ],
    [
      1764810791868.585,
      743,
      472
    ],
    [
      1764810791909.11,
      756,
      472
    ],
    [
      1764810791950.5588,
      743,
      472
    ],
    [
      1764810791988.477,
      743,
      472
    ],
    [
      1764810792031.554,
      743,
      472
    ],
    [
      1764810792067.6182,
      756,
      509
    ],
    [
      1764810792110.558,
      743,
      509
    ],
    [
      1764810792145.866,
      743,
      509
    ],
    [
      1764810792188.701,
      743,
      472
    ],
    [
      1764810792230.0579,
      743,
      491
    ],
    [
      1764810792264.533,
      731,
      472
    ],
    [
      1764810792300.523,
      756,
      528
    ],
    [
      1764810792348.4258,
      1144,
      528
    ],
    [
      1764810792391.046,
      1511,
      620
    ],
    [
      1764810792425.555,
      1511,
      639
    ],
    [
      1764810792460.38,
      1511,
      639
    ],
    [
      1764810792497.227,
      1511,
      639
    ],
    [
      1764810792531.8242,
      1511,
      639
    ],
    [
      1764810792580.769,
      1511,
      639
    ],
    [
      1764810792621.3328,
      1511,
      620
    ],
    [
      1764810792662.8262,
      1511,
      639
    ],
    [
      1764810792698.028,
      1511,
      639
    ],
    [
      1764810792731.7231,
      1499,
      602
    ],
    [
      1764810792769.1091,
      768,
      491
    ],
    [
      1764810792809.2842,
      768,
      528
    ],
    [
      1764810792844.1519,
      768,
      528
    ],
    [
      1764810792880.846,
      768,
      546
    ],
    [
      1764810792915.432,
      756,
      491
    ],
    [
      1764810792959.299,
      768,
      528
    ],
    [
      1764810793000.9502,
      781,
      509
    ],
    [
      1764810793034.595,
      768,
      397
    ],
    [
      1764810793077.034,
      768,
      528
    ],
    [
      1764810793113.051,
      768,
      528
    ],
    [
      1764810793146.985,
      768,
      528
    ],
    [
      1764810793189.507,
      768,
      528
    ],
    [
      1764810793231.252,
      768,
      528
    ],
    [
      1764810793265.264,
      756,
      472
    ],
    [
      1764810793299.9119,
      756,
      491
    ],
    [
      1764810793343.29,
      756,
      528
    ],
    [
      1764810793405.4612,
      756,
      491
    ],
    [
      1764810793458.13,
      756,
      546
    ],
    [
      1764810793499.1438,
      756,
      491
    ],
    [
      1764810793541.344,
      756,
      528
    ],
    [
      1764810793583.4482,
      756,
      491
    ],
    [
      1764810793619.2231,
      756,
      491
    ],
    [
      1764810793661.3792,
      756,
      491
    ],
    [
      1764810793703.373,
      1511,
      565
    ],
    [
      1764810793737.646,
      1511,
      602
    ],
    [
      1764810793771.6218,
      1511,
      620
    ],
    [
      1764810793812.721,
      1511,
      620
    ],
    [
      1764810793855.124,
      1511,
      620
    ],
    [
      1764810793890.057,
      1511,
      639
    ],
    [
      1764810793924.512,
      1511,
      639
    ],
    [
      1764810793965.739,
      1511,
      639
    ],
    [
      1764810794006.895,
      1511,
      639
    ],
    [
      1764810794042.0588,
      1511,
      639
    ],
    [
      1764810794076.632,
      1245,
      546
    ],
    [
      1764810794119.044,
      806,
      565
    ],
    [
      1764810794154.8281,
      781,
      565
    ],
    [
      1764810794196.223,
      781,
      565
    ],
    [
      1764810794239.157,
      781,
      565
    ],
    [
      1764810794275.2278,
      781,
      565
    ],
    [
      1764810794317.497,
      781,
      565
    ],
    [
      1764810794359.264,
      781,
      565
    ],
    [
      1764810794406.6611,
      781,
      565
    ],
    [
      1764810794443.296,
      781,
      509
    ],
    [
      1764810794485.547,
      793,
      546
    ],
    [
      1764810794527.185,
      781,
      565
    ],
    [
      1764810794563.332,
      781,
      509
    ],
    [
      1764810794605.6587,
      781,
      565
    ],
    [
      1764810794645.314,
      781,
      546
    ],
    [
      1764810794687.81,
      768,
      509
    ],
    [
      1764810794722.879,
      768,
      509
    ],
    [
      1764810794765.718,
      768,
      509
    ],
    [
      1764810794807.369,
      768,
      509
    ],
    [
      1764810794861.748,
      768,
      509
    ],
    [
      1764810794899.064,
      756,
      491
    ],
    [
      1764810794940.404,
      756,
      546
    ],
    [
      1764810794977.4348,
      756,
      546
    ],
    [
      1764810795020.25,
      756,
      546
    ],
    [
      1764810795056.0862,
      743,
      546
    ],
    [
      1764810795090.0413,
      743,
      509
    ],
    [
      1764810795125.0142,
      743,
      509
    ],
    [
      1764810795167.906,
      743,
      509
    ],
    [
      1764810795202.045,
      619,
      528
    ],
    [
      1764810795244.596,
      37,
      528
    ],
    [
      1764810795285.938,
      25,
      528
    ],
    [
      1764810795327.0212,
      25,
      528
    ],
    [
      1764810795361.5671,
      25,
      546
    ],
    [
      1764810795396.616,
      25,
      546
    ],
    [
      1764810795431.2163,
      12,
      546
    ],
    [
      1764810795468.508,
      12,
      546
    ],
    [
      1764810795512.495,
      12,
      546
    ],
    [
      1764810795549.903,
      12,
      546
    ],
    [
      1764810795585.221,
      111,
      583
    ],
    [
      1764810795620.517,
      706,
      509
    ],
    [
      1764810795660.2922,
      706,
      583
    ],
    [
      1764810795702.383,
      694,
      583
    ],
    [
      1764810795737.118,
      694,
      583
    ],
    [
      1764810795778.396,
      706,
      602
    ],
    [
      1764810795819.368,
      694,
      602
    ],
    [
      1764810795853.983,
      706,
      620
    ],
    [
      1764810795889.7212,
      706,
      639
    ],
    [
      1764810795924.5232,
      694,
      620
    ],
    [
      1764810795967.654,
      706,
      620
    ],
    [
      1764810796006.545,
      706,
      639
    ],
    [
      1764810796042.422,
      706,
      620
    ],
    [
      1764810796076.811,
      706,
      620
    ],
    [
      1764810796113.527,
      706,
      602
    ],
    [
      1764810796148.306,
      718,
      583
    ],
    [
      1764810796189.951,
      718,
      546
    ],
    [
      1764810796237.6692,
      731,
      565
    ],
    [
      1764810796279.152,
      731,
      546
    ],
    [
      1764810796313.843,
      731,
      546
    ],
    [
      1764810796356.834,
      731,
      509
    ],
    [
      1764810796397.537,
      743,
      509
    ],
    [
      1764810796432.8599,
      743,
      509
    ],
    [
      1764810796473.881,
      1106,
      509
    ],
    [
      1764810796509.242,
      1511,
      620
    ],
    [
      1764810796545.834,
      1511,
      620
    ],
    [
      1764810796580.647,
      1511,
      620
    ],
    [
      1764810796623.237,
      1511,
      620
    ],
    [
      1764810796658.2642,
      1511,
      620
    ],
    [
      1764810796697.6353,
      1511,
      620
    ],
    [
      1764810796732.612,
      1511,
      602
    ],
    [
      1764810796775.1082,
      1511,
      602
    ],
    [
      1764810796811.9302,
      1511,
      583
    ],
    [
      1764810796854.749,
      1006,
      491
    ],
    [
      1764810796890.978,
      843,
      509
    ],
    [
      1764810796931.759,
      843,
      528
    ],
    [
      1764810796966.936,
      831,
      435
    ],
    [
      1764810797003.0469,
      843,
      509
    ],
    [
      1764810797045.5781,
      843,
      509
    ],
    [
      1764810797086.872,
      843,
      509
    ],
    [
      1764810797121.554,
      831,
      528
    ],
    [
      1764810797154.686,
      843,
      528
    ],
    [
      1764810797197.354,
      843,
      509
    ],
    [
      1764810797239.621,
      831,
      491
    ],
    [
      1764810797274.2751,
      831,
      491
    ],
    [
      1764810797308.241,
      831,
      491
    ],
    [
      1764810797345.2603,
      818,
      491
    ],
    [
      1764810797386.04,
      818,
      453
    ],
    [
      1764810797421.4988,
      818,
      491
    ],
    [
      1764810797464.058,
      806,
      491
    ],
    [
      1764810797498.381,
      806,
      453
    ],
    [
      1764810797540.575,
      793,
      435
    ],
    [
      1764810797583.483,
      806,
      472
    ],
    [
      1764810797617.593,
      793,
      453
    ],
    [
      1764810797651.9922,
      793,
      491
    ],
    [
      1764810797688.8608,
      781,
      472
    ],
    [
      1764810797723.9548,
      445,
      416
    ],
    [
      1764810797767.045,
      25,
      491
    ],
    [
      1764810797801.586,
      12,
      491
    ],
    [
      1764810797835.335,
      12,
      491
    ],
    [
      1764810797878.711,
      12,
      472
    ],
    [
      1764810797914.4858,
      12,
      472
    ],
    [
      1764810797956.928,
      12,
      472
    ],
    [
      1764810797996.7517,
      0,
      453
    ],
    [
      1764810798039.171,
      0,
      472
    ],
    [
      1764810798073.7112,
      0,
      472
    ],
    [
      1764810798108.064,
      0,
      453
    ],
    [
      1764810798150.614,
      0,
      453
    ],
    [
      1764810798186.2942,
      12,
      453
    ],
    [
      1764810798228.3362,
      12,
      453
    ],
    [
      1764810798269.7861,
      619,
      416
    ],
    [
      1764810798311.147,
      793,
      509
    ],
    [
      1764810798346.367,
      781,
      472
    ],
    [
      1764810798380.807,
      793,
      416
    ],
    [
      1764810798423.5251,
      793,
      472
    ],
    [
      1764810798458.604,
      806,
      397
    ],
    [
      1764810798500.8728,
      806,
      397
    ],
    [
      1764810798542.353,
      806,
      397
    ],
    [
      1764810798578.339,
      818,
      397
    ],
    [
      1764810798620.8372,
      793,
      453
    ],
    [
      1764810798661.608,
      806,
      453
    ],
    [
      1764810798697.726,
      806,
      453
    ],
    [
      1764810798730.7642,
      818,
      378
    ],
    [
      1764810798764.544,
      806,
      453
    ],
    [
      1764810798807.28,
      806,
      397
    ],
    [
      1764810798841.527,
      806,
      397
    ],
    [
      1764810798877.1929,
      768,
      453
    ],
    [
      1764810798919.32,
      768,
      453
    ],
    [
      1764810798954.376,
      756,
      453
    ],
    [
      1764810798995.1648,
      756,
      453
    ],
    [
      1764810799037.016,
      756,
      453
    ],
    [
      1764810799078.0361,
      756,
      416
    ],
    [
      1764810799112.8042,
      756,
      416
    ],
    [
      1764810799148.933,
      756,
      416
    ],
    [
      1764810799191.6968,
      756,
      453
    ],
    [
      1764810799225.514,
      743,
      416
    ],
    [
      1764810799259.3137,
      743,
      453
    ],
    [
      1764810799301.856,
      743,
      453
    ],
    [
      1764810799343.3162,
      743,
      416
    ],
    [
      1764810799380.547,
      743,
      416
    ],
    [
      1764810799423.521,
      756,
      453
    ],
    [
      1764810799462.751,
      756,
      416
    ],
    [
      1764810799498.921,
      756,
      453
    ],
    [
      1764810799541.444,
      756,
      453
    ],
    [
      1764810799582.4902,
      756,
      416
    ],
    [
      1764810799618.016,
      1068,
      453
    ],
    [
      1764810799659.035,
      1308,
      509
    ],
    [
      1764810799693.133,
      1308,
      509
    ],
    [
      1764810799729.3608,
      1308,
      509
    ],
    [
      1764810799764.743,
      1321,
      509
    ],
    [
      1764810799807.256,
      1321,
      509
    ],
    [
      1764810799842.782,
      1321,
      509
    ],
    [
      1764810799877.9788,
      1321,
      509
    ],
    [
      1764810799912.862,
      1321,
      509
    ],
    [
      1764810799947.305,
      1321,
      509
    ],
    [
      1764810799990.0269,
      1333,
      509
    ],
    [
      1764810800031.321,
      793,
      416
    ],
    [
      1764810800066.58,
      793,
      491
    ],
    [
      1764810800100.6602,
      781,
      453
    ],
    [
      1764810800141.778,
      793,
      491
    ],
    [
      1764810800183.1912,
      781,
      435
    ],
    [
      1764810800217.992,
      781,
      453
    ],
    [
      1764810800252.219,
      781,
      453
    ],
    [
      1764810800289.0361,
      781,
      416
    ],
    [
      1764810800323.531,
      781,
      491
    ],
    [
      1764810800364.254,
      781,
      491
    ],
    [
      1764810800407.5032,
      781,
      453
    ],
    [
      1764810800443.61,
      781,
      453
    ],
    [
      1764810800485.908,
      781,
      453
    ],
    [
      1764810800526.6108,
      768,
      435
    ],
    [
      1764810800562.5442,
      768,
      453
    ],
    [
      1764810800602.294,
      781,
      453
    ],
    [
      1764810800637.456,
      781,
      453
    ],
    [
      1764810800678.313,
      781,
      491
    ],
    [
      1764810800713.5151,
      768,
      453
    ],
    [
      1764810800748.111,
      470,
      472
    ],
    [
      1764810800791.064,
      124,
      491
    ],
    [
      1764810800831.813,
      124,
      491
    ],
    [
      1764810800868.6577,
      124,
      491
    ],
    [
      1764810800905.4312,
      111,
      491
    ],
    [
      1764810800940.1338,
      111,
      491
    ],
    [
      1764810800984.041,
      111,
      491
    ],
    [
      1764810801019.113,
      136,
      528
    ],
    [
      1764810801058.6409,
      99,
      509
    ],
    [
      1764810801093.912,
      124,
      528
    ],
    [
      1764810801129.444,
      124,
      546
    ],
    [
      1764810801163.832,
      656,
      359
    ],
    [
      1764810801207.673,
      706,
      397
    ],
    [
      1764810801242.6948,
      706,
      435
    ],
    [
      1764810801283.211,
      706,
      416
    ],
    [
      1764810801325.9011,
      718,
      472
    ],
    [
      1764810801368.1018,
      706,
      472
    ],
    [
      1764810801402.934,
      718,
      453
    ],
    [
      1764810801437.254,
      718,
      491
    ],
    [
      1764810801474.5159,
      718,
      435
    ],
    [
      1764810801515.424,
      718,
      472
    ],
    [
      1764810801557.2632,
      718,
      435
    ],
    [
      1764810801599.1208,
      718,
      472
    ],
    [
      1764810801635.162,
      718,
      435
    ],
    [
      1764810801677.7861,
      718,
      435
    ],
    [
      1764810801717.3472,
      718,
      435
    ],
    [
      1764810801759.386,
      718,
      435
    ],
    [
      1764810801794.839,
      718,
      435
    ],
    [
      1764810801837.201,
      731,
      435
    ],
    [
      1764810801879.5378,
      731,
      472
    ],
    [
      1764810801915.401,
      718,
      435
    ],
    [
      1764810801955.9062,
      718,
      435
    ],
    [
      1764810801998.368,
      718,
      472
    ],
    [
      1764810802039.399,
      718,
      435
    ],
    [
      1764810802075.393,
      644,
      397
    ],
    [
      1764810802117.573,
      0,
      453
    ],
    [
      1764810802159.5159,
      0,
      435
    ],
    [
      1764810802193.779,
      0,
      491
    ],
    [
      1764810802228.294,
      0,
      491
    ],
    [
      1764810802271.008,
      0,
      491
    ],
    [
      1764810802307.2168,
      0,
      472
    ],
    [
      1764810802349.4612,
      0,
      491
    ],
    [
      1764810802384.4968,
      0,
      509
    ],
    [
      1764810802417.711,
      0,
      491
    ],
    [
      1764810802452.586,
      532,
      453
    ],
    [
      1764810802494.955,
      656,
      509
    ],
    [
      1764810802530.049,
      669,
      509
    ],
    [
      1764810802564.789,
      656,
      509
    ],
    [
      1764810802607.2278,
      669,
      509
    ],
    [
      1764810802641.955,
      669,
      509
    ],
    [
      1764810802676.4958,
      681,
      491
    ],
    [
      1764810802719.312,
      681,
      491
    ],
    [
      1764810802754.3171,
      694,
      491
    ],
    [
      1764810802796.537,
      681,
      491
    ],
    [
      1764810802839.561,
      681,
      491
    ],
    [
      1764810802873.9067,
      681,
      472
    ],
    [
      1764810802908.242,
      681,
      491
    ],
    [
      1764810802949.758,
      681,
      491
    ],
    [
      1764810802991.564,
      694,
      472
    ],
    [
      1764810803026.5,
      1131,
      491
    ],
    [
      1764810803061.069,
      1182,
      509
    ],
    [
      1764810803101.25,
      1182,
      528
    ],
    [
      1764810803143.209,
      1169,
      509
    ],
    [
      1764810803179.104,
      1182,
      509
    ],
    [
      1764810803221.4712,
      1182,
      491
    ],
    [
      1764810803257.545,
      1182,
      491
    ],
    [
      1764810803291.1802,
      1182,
      491
    ],
    [
      1764810803332.223,
      1182,
      491
    ],
    [
      1764810803373.8,
      1182,
      491
    ],
    [
      1764810803415.1812,
      1182,
      491
    ],
    [
      1764810803450.167,
      1144,
      472
    ],
    [
      1764810803484.1257,
      768,
      453
    ],
    [
      1764810803521.398,
      768,
      453
    ],
    [
      1764810803568.5142,
      768,
      435
    ],
    [
      1764810803603.0479,
      768,
      453
    ],
    [
      1764810803637.717,
      756,
      435
    ],
    [
      1764810803674.6162,
      756,
      453
    ],
    [
      1764810803708.529,
      756,
      453
    ],
    [
      1764810803751.913,
      756,
      435
    ],
    [
      1764810803791.199,
      756,
      435
    ],
    [
      1764810803827.2341,
      756,
      435
    ],
    [
      1764810803870.062,
      743,
      435
    ],
    [
      1764810803911.0908,
      743,
      435
    ],
    [
      1764810803947.394,
      743,
      435
    ],
    [
      1764810803990.0898,
      743,
      416
    ],
    [
      1764810804031.304,
      743,
      416
    ],
    [
      1764810804066.549,
      743,
      416
    ],
    [
      1764810804109.144,
      743,
      397
    ],
    [
      1764810804151.318,
      1094,
      416
    ],
    [
      1764810804185.702,
      1422,
      472
    ],
    [
      1764810804220.604,
      1422,
      491
    ],
    [
      1764810804261.389,
      1448,
      491
    ],
    [
      1764810804303.41,
      1461,
      491
    ],
    [
      1764810804339.0022,
      1473,
      491
    ],
    [
      1764810804374.274,
      1473,
      491
    ],
    [
      1764810804410.354,
      1473,
      491
    ],
    [
      1764810804445.009,
      1473,
      491
    ],
    [
      1764810804485.3079,
      1473,
      491
    ],
    [
      1764810804527.3699,
      1397,
      472
    ],
    [
      1764810804562.6528,
      781,
      453
    ],
    [
      1764810804604.695,
      781,
      453
    ],
    [
      1764810804648.202,
      781,
      453
    ],
    [
      1764810804695.01,
      781,
      435
    ],
    [
      1764810804729.9998,
      781,
      453
    ],
    [
      1764810804773.01,
      781,
      453
    ],
    [
      1764810804815.0,
      768,
      435
    ],
    [
      1764810804852.911,
      781,
      435
    ],
    [
      1764810804895.6301,
      768,
      453
    ],
    [
      1764810804929.7002,
      768,
      453
    ],
    [
      1764810804964.9868,
      768,
      435
    ],
    [
      1764810805007.23,
      768,
      435
    ],
    [
      1764810805042.5977,
      768,
      435
    ],
    [
      1764810805076.649,
      768,
      435
    ],
    [
      1764810805119.019,
      768,
      416
    ],
    [
      1764810805154.4377,
      768,
      416
    ],
    [
      1764810805196.9978,
      768,
      416
    ],
    [
      1764810805233.223,
      768,
      416
    ],
    [
      1764810805266.7441,
      756,
      416
    ],
    [
      1764810805308.9412,
      768,
      416
    ],
    [
      1764810805352.247,
      756,
      416
    ],
    [
      1764810805387.389,
      272,
      453
    ],
    [
      1764810805429.0051,
      37,
      435
    ],
    [
      1764810805470.9539,
      25,
      435
    ],
    [
      1764810805506.826,
      25,
      435
    ],
    [
      1764810805550.573,
      25,
      435
    ],
    [
      1764810805592.069,
      25,
      435
    ],
    [
      1764810805638.67,
      25,
      453
    ],
    [
      1764810805675.568,
      25,
      453
    ],
    [
      1764810805711.019,
      25,
      453
    ],
    [
      1764810805748.2878,
      544,
      359
    ],
    [
      1764810805791.007,
      532,
      378
    ],
    [
      1764810805838.5952,
      532,
      378
    ],
    [
      1764810805879.505,
      532,
      397
    ],
    [
      1764810805915.3188,
      544,
      416
    ],
    [
      1764810805957.57,
      544,
      397
    ],
    [
      1764810805993.3728,
      544,
      435
    ],
    [
      1764810806027.7979,
      694,
      416
    ],
    [
      1764810806068.815,
      806,
      453
    ],
    [
      1764810806111.084,
      806,
      509
    ],
    [
      1764810806147.744,
      818,
      509
    ],
    [
      1764810806191.7068,
      818,
      509
    ],
    [
      1764810806226.6172,
      818,
      509
    ],
    [
      1764810806260.5051,
      818,
      509
    ],
    [
      1764810806301.239,
      818,
      472
    ],
    [
      1764810806342.148,
      1511,
      981
    ],
    [
      1764810806381.2961,
      1511,
      981
    ],
    [
      1764810806423.46,
      1169,
      981
    ],
    [
      1764810806460.314,
      793,
      546
    ],
    [
      1764810806502.994,
      781,
      378
    ],
    [
      1764810806543.1738,
      781,
      378
    ],
    [
      1764810806578.885,
      781,
      397
    ],
    [
      1764810806612.8262,
      781,
      397
    ],
    [
      1764810806655.6,
      768,
      397
    ],
    [
      1764810806689.922,
      768,
      397
    ],
    [
      1764810806725.134,
      781,
      322
    ],
    [
      1764810806765.614,
      768,
      397
    ],
    [
      1764810806806.989,
      768,
      397
    ],
    [
      1764810806843.209,
      781,
      378
    ],
    [
      1764810806885.756,
      781,
      397
    ],
    [
      1764810806927.7551,
      781,
      397
    ],
    [
      1764810806975.5771,
      793,
      416
    ],
    [
      1764810807010.3738,
      781,
      416
    ],
    [
      1764810807045.519,
      781,
      378
    ],
    [
      1764810807087.8457,
      781,
      397
    ],
    [
      1764810807122.88,
      781,
      416
    ],
    [
      1764810807157.061,
      793,
      397
    ],
    [
      1764810807205.666,
      781,
      397
    ],
    [
      1764810807247.289,
      781,
      416
    ],
    [
      1764810807282.305,
      793,
      359
    ],
    [
      1764810807316.5781,
      781,
      378
    ],
    [
      1764810807358.9758,
      781,
      435
    ],
    [
      1764810807395.599,
      781,
      435
    ],
    [
      1764810807436.226,
      793,
      378
    ],
    [
      1764810807480.314,
      781,
      416
    ],
    [
      1764810807514.8062,
      793,
      453
    ],
    [
      1764810807548.855,
      793,
      453
    ],
    [
      1764810807591.435,
      793,
      453
    ],
    [
      1764810807627.381,
      793,
      416
    ],
    [
      1764810807668.469,
      806,
      453
    ],
    [
      1764810807709.936,
      793,
      397
    ],
    [
      1764810807745.17,
      793,
      416
    ],
    [
      1764810807779.178,
      793,
      416
    ],
    [
      1764810807815.368,
      793,
      416
    ],
    [
      1764810807850.098,
      793,
      453
    ],
    [
      1764810807891.655,
      793,
      416
    ],
    [
      1764810807932.4429,
      793,
      453
    ],
    [
      1764810807975.141,
      731,
      453
    ],
    [
      1764810808010.453,
      495,
      416
    ],
    [
      1764810808045.295,
      482,
      435
    ],
    [
      1764810808082.46,
      470,
      528
    ],
    [
      1764810808122.5833,
      470,
      583
    ],
    [
      1764810808156.498,
      470,
      675
    ],
    [
      1764810808199.1292,
      458,
      767
    ],
    [
      1764810808234.388,
      445,
      785
    ],
    [
      1764810808269.0872,
      445,
      767
    ],
    [
      1764810808305.4668,
      731,
      730
    ],
    [
      1764810808346.303,
      768,
      803
    ],
    [
      1764810808387.36,
      768,
      821
    ],
    [
      1764810808429.739,
      781,
      839
    ],
    [
      1764810808471.107,
      793,
      875
    ],
    [
      1764810808506.758,
      793,
      875
    ],
    [
      1764810808541.3079,
      806,
      839
    ],
    [
      1764810808581.4421,
      806,
      785
    ],
    [
      1764810808617.857,
      818,
      712
    ],
    [
      1764810808652.0122,
      818,
      675
    ],
    [
      1764810808688.3892,
      831,
      675
    ],
    [
      1764810808723.418,
      831,
      620
    ],
    [
      1764810808766.061,
      843,
      620
    ],
    [
      1764810808806.777,
      843,
      657
    ],
    [
      1764810808843.2332,
      831,
      639
    ],
    [
      1764810808885.8518,
      831,
      528
    ],
    [
      1764810808926.8943,
      806,
      712
    ],
    [
      1764810808962.0327,
      793,
      675
    ],
    [
      1764810808996.9248,
      793,
      639
    ],
    [
      1764810809037.7312,
      793,
      639
    ],
    [
      1764810809080.662,
      781,
      675
    ],
    [
      1764810809117.085,
      781,
      639
    ],
    [
      1764810809159.4539,
      781,
      565
    ],
    [
      1764810809193.4778,
      781,
      657
    ],
    [
      1764810809228.7822,
      781,
      620
    ],
    [
      1764810809269.444,
      781,
      657
    ],
    [
      1764810809311.687,
      781,
      639
    ],
    [
      1764810809346.004,
      781,
      620
    ],
    [
      1764810809381.251,
      781,
      639
    ],
    [
      1764810809423.416,
      781,
      639
    ],
    [
      1764810809458.184,
      781,
      639
    ],
    [
      1764810809498.838,
      806,
      639
    ],
    [
      1764810809541.149,
      1131,
      639
    ],
    [
      1764810809581.7358,
      1131,
      657
    ],
    [
      1764810809623.21,
      1131,
      657
    ],
    [
      1764810809658.393,
      1131,
      657
    ],
    [
      1764810809693.271,
      1131,
      657
    ],
    [
      1764810809733.486,
      1131,
      657
    ],
    [
      1764810809770.013,
      1131,
      657
    ],
    [
      1764810809804.3762,
      1131,
      657
    ],
    [
      1764810809846.939,
      1144,
      583
    ],
    [
      1764810809881.8372,
      1131,
      675
    ],
    [
      1764810809916.605,
      1131,
      675
    ],
    [
      1764810809957.001,
      1131,
      675
    ],
    [
      1764810809999.3643,
      1131,
      675
    ],
    [
      1764810810035.458,
      743,
      565
    ],
    [
      1764810810077.543,
      433,
      620
    ],
    [
      1764810810119.6602,
      420,
      639
    ],
    [
      1764810810155.375,
      420,
      639
    ],
    [
      1764810810195.1548,
      420,
      639
    ],
    [
      1764810810238.465,
      420,
      657
    ],
    [
      1764810810279.3071,
      433,
      639
    ],
    [
      1764810810315.894,
      433,
      639
    ],
    [
      1764810810357.915,
      433,
      620
    ],
    [
      1764810810405.513,
      433,
      620
    ],
    [
      1764810810447.5698,
      433,
      620
    ],
    [
      1764810810483.103,
      433,
      620
    ],
    [
      1764810810518.168,
      619,
      602
    ],
    [
      1764810810558.751,
      793,
      657
    ],
    [
      1764810810594.646,
      806,
      657
    ],
    [
      1764810810627.79,
      793,
      639
    ],
    [
      1764810810671.7817,
      793,
      639
    ],
    [
      1764810810707.831,
      806,
      657
    ],
    [
      1764810810751.271,
      806,
      657
    ],
    [
      1764810810787.084,
      818,
      675
    ],
    [
      1764810810830.4683,
      831,
      657
    ],
    [
      1764810810877.685,
      818,
      620
    ],
    [
      1764810810919.432,
      806,
      546
    ],
    [
      1764810810954.5522,
      806,
      509
    ],
    [
      1764810810996.73,
      818,
      435
    ],
    [
      1764810811039.647,
      818,
      397
    ],
    [
      1764810811075.307,
      818,
      397
    ],
    [
      1764810811115.9402,
      806,
      359
    ],
    [
      1764810811156.835,
      806,
      416
    ],
    [
      1764810811199.132,
      806,
      397
    ],
    [
      1764810811234.404,
      806,
      435
    ],
    [
      1764810811268.667,
      793,
      397
    ],
    [
      1764810811316.606,
      793,
      416
    ],
    [
      1764810811358.4111,
      781,
      435
    ],
    [
      1764810811398.897,
      781,
      453
    ],
    [
      1764810811434.091,
      793,
      453
    ],
    [
      1764810811468.79,
      781,
      491
    ],
    [
      1764810811505.129,
      781,
      453
    ],
    [
      1764810811547.488,
      781,
      453
    ],
    [
      1764810811589.006,
      768,
      453
    ],
    [
      1764810811631.315,
      768,
      472
    ],
    [
      1764810811666.4153,
      768,
      453
    ],
    [
      1764810811709.227,
      768,
      472
    ],
    [
      1764810811749.675,
      756,
      453
    ],
    [
      1764810811791.401,
      768,
      472
    ],
    [
      1764810811826.632,
      768,
      472
    ],
    [
      1764810811861.3171,
      756,
      472
    ],
    [
      1764810811903.3052,
      756,
      453
    ],
    [
      1764810811938.925,
      768,
      491
    ],
    [
      1764810811981.521,
      768,
      509
    ],
    [
      1764810812021.097,
      656,
      491
    ],
    [
      1764810812063.2598,
      185,
      416
    ],
    [
      1764810812098.5532,
      210,
      528
    ],
    [
      1764810812141.212,
      210,
      528
    ],
    [
      1764810812183.1182,
      210,
      528
    ],
    [
      1764810812226.8328,
      210,
      509
    ],
    [
      1764810812260.727,
      210,
      509
    ],
    [
      1764810812296.845,
      210,
      528
    ],
    [
      1764810812331.026,
      210,
      528
    ],
    [
      1764810812367.2332,
      210,
      509
    ],
    [
      1764810812402.0159,
      210,
      509
    ],
    [
      1764810812437.217,
      210,
      491
    ],
    [
      1764810812477.519,
      210,
      509
    ],
    [
      1764810812519.082,
      210,
      491
    ],
    [
      1764810812557.198,
      210,
      509
    ],
    [
      1764810812599.139,
      210,
      472
    ],
    [
      1764810812633.754,
      210,
      472
    ],
    [
      1764810812668.395,
      210,
      472
    ],
    [
      1764810812709.2778,
      222,
      472
    ],
    [
      1764810812751.3289,
      731,
      453
    ],
    [
      1764810812786.455,
      793,
      491
    ],
    [
      1764810812821.155,
      793,
      491
    ],
    [
      1764810812863.517,
      793,
      509
    ],
    [
      1764810812900.3752,
      793,
      491
    ],
    [
      1764810812940.754,
      793,
      491
    ],
    [
      1764810812983.114,
      793,
      491
    ],
    [
      1764810813018.443,
      793,
      472
    ],
    [
      1764810813052.402,
      793,
      472
    ],
    [
      1764810813088.9639,
      793,
      472
    ],
    [
      1764810813123.877,
      793,
      472
    ],
    [
      1764810813158.013,
      793,
      472
    ],
    [
      1764810813199.6548,
      793,
      453
    ],
    [
      1764810813234.7698,
      793,
      453
    ],
    [
      1764810813277.616,
      806,
      435
    ],
    [
      1764810813319.1118,
      806,
      453
    ],
    [
      1764810813355.1628,
      806,
      435
    ],
    [
      1764810813395.993,
      793,
      453
    ],
    [
      1764810813437.69,
      793,
      453
    ],
    [
      1764810813479.511,
      793,
      453
    ],
    [
      1764810813515.367,
      793,
      453
    ],
    [
      1764810813557.7732,
      793,
      453
    ],
    [
      1764810813604.8901,
      781,
      453
    ],
    [
      1764810813647.6008,
      781,
      453
    ],
    [
      1764810813688.72,
      781,
      472
    ],
    [
      1764810813725.087,
      768,
      491
    ],
    [
      1764810813767.761,
      768,
      472
    ],
    [
      1764810813802.728,
      768,
      491
    ],
    [
      1764810813843.4219,
      768,
      453
    ],
    [
      1764810813886.036,
      756,
      491
    ],
    [
      1764810813926.6409,
      768,
      472
    ],
    [
      1764810813962.023,
      768,
      453
    ],
    [
      1764810813996.631,
      756,
      472
    ],
    [
      1764810814039.183,
      756,
      491
    ],
    [
      1764810814073.499,
      756,
      472
    ],
    [
      1764810814110.168,
      1068,
      453
    ],
    [
      1764810814146.2651,
      1257,
      509
    ],
    [
      1764810814181.447,
      1257,
      509
    ],
    [
      1764810814223.256,
      1257,
      509
    ],
    [
      1764810814258.1702,
      1270,
      509
    ],
    [
      1764810814298.744,
      1270,
      509
    ],
    [
      1764810814341.519,
      1283,
      509
    ],
    [
      1764810814376.58,
      1283,
      509
    ],
    [
      1764810814414.002,
      1283,
      528
    ],
    [
      1764810814455.394,
      1283,
      528
    ],
    [
      1764810814491.2961,
      1295,
      528
    ],
    [
      1764810814532.257,
      1295,
      528
    ],
    [
      1764810814573.8398,
      1295,
      528
    ],
    [
      1764810814615.4229,
      1295,
      528
    ],
    [
      1764810814651.0542,
      1295,
      528
    ],
    [
      1764810814685.462,
      1144,
      472
    ],
    [
      1764810814727.5469,
      856,
      453
    ],
    [
      1764810814762.5442,
      831,
      453
    ],
    [
      1764810814797.2622,
      831,
      453
    ],
    [
      1764810814839.751,
      818,
      453
    ],
    [
      1764810814874.6062,
      818,
      472
    ],
    [
      1764810814917.961,
      818,
      453
    ],
    [
      1764810814958.859,
      806,
      453
    ],
    [
      1764810814999.046,
      768,
      472
    ],
    [
      1764810815034.392,
      681,
      491
    ],
    [
      1764810815068.466,
      669,
      491
    ],
    [
      1764810815111.9749,
      681,
      509
    ],
    [
      1764810815148.4812,
      669,
      491
    ],
    [
      1764810815190.6401,
      681,
      509
    ],
    [
      1764810815230.9802,
      681,
      509
    ],
    [
      1764810815266.386,
      681,
      509
    ],
    [
      1764810815301.379,
      681,
      491
    ],
    [
      1764810815337.5518,
      681,
      491
    ],
    [
      1764810815371.957,
      681,
      491
    ],
    [
      1764810815415.857,
      669,
      491
    ],
    [
      1764810815454.1912,
      669,
      509
    ],
    [
      1764810815496.213,
      669,
      491
    ],
    [
      1764810815532.9038,
      681,
      509
    ],
    [
      1764810815569.4739,
      681,
      472
    ],
    [
      1764810815604.039,
      681,
      472
    ],
    [
      1764810815646.525,
      681,
      472
    ],
    [
      1764810815685.587,
      681,
      453
    ],
    [
      1764810815727.689,
      681,
      472
    ],
    [
      1764810815763.113,
      681,
      453
    ],
    [
      1764810815805.0881,
      681,
      453
    ],
    [
      1764810815848.569,
      681,
      453
    ],
    [
      1764810815889.719,
      681,
      453
    ],
    [
      1764810815924.0178,
      681,
      453
    ],
    [
      1764810815967.5469,
      681,
      453
    ],
    [
      1764810816001.4238,
      681,
      453
    ],
    [
      1764810816036.8098,
      681,
      453
    ],
    [
      1764810816079.4421,
      681,
      453
    ],
    [
      1764810816127.5452,
      681,
      453
    ],
    [
      1764810816163.351,
      669,
      435
    ],
    [
      1764810816204.0288,
      893,
      378
    ],
    [
      1764810816246.6572,
      1043,
      397
    ],
    [
      1764810816281.74,
      1043,
      416
    ],
    [
      1764810816317.1892,
      1043,
      397
    ],
    [
      1764810816357.425,
      1056,
      416
    ],
    [
      1764810816399.519,
      1056,
      397
    ],
    [
      1764810816434.648,
      1056,
      397
    ],
    [
      1764810816476.6099,
      1068,
      397
    ],
    [
      1764810816519.478,
      1068,
      416
    ],
    [
      1764810816554.507,
      1068,
      416
    ],
    [
      1764810816595.02,
      1068,
      416
    ],
    [
      1764810816637.7751,
      1068,
      416
    ],
    [
      1764810816680.207,
      1068,
      416
    ],
    [
      1764810816715.489,
      1068,
      416
    ],
    [
      1764810816758.2432,
      1068,
      416
    ],
    [
      1764810816806.251,
      1056,
      435
    ],
    [
      1764810816842.4312,
      1056,
      416
    ],
    [
      1764810816877.824,
      1056,
      416
    ],
    [
      1764810816915.3962,
      1056,
      435
    ],
    [
      1764810816951.261,
      1056,
      416
    ],
    [
      1764810816987.6292,
      1056,
      416
    ],
    [
      1764810817028.073,
      1056,
      416
    ],
    [
      1764810817070.25,
      893,
      397
    ],
    [
      1764810817111.842,
      694,
      416
    ],
    [
      1764810817147.1428,
      694,
      416
    ],
    [
      1764810817189.884,
      681,
      416
    ],
    [
      1764810817232.477,
      681,
      416
    ],
    [
      1764810817265.422,
      681,
      397
    ],
    [
      1764810817301.095,
      681,
      416
    ],
    [
      1764810817342.0852,
      681,
      416
    ],
    [
      1764810817383.6929,
      681,
      378
    ],
    [
      1764810817419.005,
      681,
      397
    ],
    [
      1764810817453.2092,
      681,
      397
    ],
    [
      1764810817494.2688,
      681,
      435
    ],
    [
      1764810817535.789,
      681,
      435
    ],
    [
      1764810817571.0652,
      681,
      416
    ],
    [
      1764810817613.497,
      681,
      416
    ],
    [
      1764810817654.266,
      681,
      435
    ],
    [
      1764810817696.295,
      681,
      435
    ],
    [
      1764810817730.295,
      681,
      453
    ],
    [
      1764810817772.692,
      681,
      435
    ],
    [
      1764810817815.5269,
      681,
      416
    ],
    [
      1764810817850.873,
      681,
      416
    ],
    [
      1764810817885.109,
      681,
      435
    ],
    [
      1764810817921.549,
      694,
      416
    ],
    [
      1764810817962.262,
      681,
      416
    ],
    [
      1764810817997.4202,
      681,
      435
    ],
    [
      1764810818039.416,
      681,
      435
    ],
    [
      1764810818076.0781,
      681,
      435
    ],
    [
      1764810818111.222,
      731,
      453
    ],
    [
      1764810818149.547,
      1068,
      435
    ],
    [
      1764810818189.412,
      1068,
      453
    ],
    [
      1764810818231.716,
      1081,
      472
    ],
    [
      1764810818266.691,
      1094,
      453
    ],
    [
      1764810818309.602,
      1094,
      472
    ],
    [
      1764810818350.028,
      1094,
      472
    ],
    [
      1764810818391.736,
      1094,
      472
    ],
    [
      1764810818425.569,
      1106,
      472
    ],
    [
      1764810818460.364,
      1106,
      472
    ],
    [
      1764810818496.56,
      1106,
      472
    ],
    [
      1764810818531.543,
      1094,
      453
    ],
    [
      1764810818573.335,
      1106,
      472
    ],
    [
      1764810818616.4092,
      1106,
      472
    ],
    [
      1764810818649.8052,
      1106,
      491
    ],
    [
      1764810818684.0762,
      1094,
      472
    ],
    [
      1764810818727.288,
      1094,
      472
    ],
    [
      1764810818762.414,
      1094,
      491
    ],
    [
      1764810818796.853,
      1094,
      491
    ],
    [
      1764810818838.746,
      1081,
      491
    ],
    [
      1764810818872.4512,
      1081,
      491
    ],
    [
      1764810818907.383,
      1094,
      472
    ],
    [
      1764810818949.5837,
      1081,
      472
    ],
    [
      1764810818991.873,
      1081,
      472
    ],
    [
      1764810819028.7878,
      1068,
      472
    ],
    [
      1764810819071.2969,
      656,
      416
    ],
    [
      1764810819111.884,
      656,
      435
    ],
    [
      1764810819146.923,
      656,
      435
    ],
    [
      1764810819190.273,
      656,
      472
    ],
    [
      1764810819231.6858,
      656,
      472
    ],
    [
      1764810819267.184,
      656,
      397
    ],
    [
      1764810819301.6792,
      656,
      416
    ],
    [
      1764810819342.825,
      656,
      416
    ],
    [
      1764810819379.351,
      656,
      416
    ],
    [
      1764810819421.51,
      644,
      453
    ],
    [
      1764810819463.753,
      656,
      397
    ],
    [
      1764810819499.0662,
      656,
      397
    ],
    [
      1764810819547.8289,
      644,
      397
    ],
    [
      1764810819589.289,
      656,
      453
    ],
    [
      1764810819630.717,
      656,
      416
    ],
    [
      1764810819666.157,
      669,
      416
    ],
    [
      1764810819700.876,
      669,
      397
    ],
    [
      1764810819743.796,
      669,
      378
    ],
    [
      1764810819778.3418,
      669,
      416
    ],
    [
      1764810819821.18,
      669,
      397
    ],
    [
      1764810819862.112,
      669,
      453
    ],
    [
      1764810819903.572,
      681,
      416
    ],
    [
      1764810819940.429,
      681,
      416
    ],
    [
      1764810819982.1812,
      681,
      397
    ],
    [
      1764810820023.06,
      681,
      397
    ],
    [
      1764810820059.102,
      681,
      397
    ],
    [
      1764810820093.364,
      694,
      416
    ],
    [
      1764810820135.7498,
      694,
      435
    ],
    [
      1764810820171.4138,
      681,
      378
    ],
    [
      1764810820214.252,
      482,
      435
    ],
    [
      1764810820253.5989,
      458,
      341
    ],
    [
      1764810820295.681,
      445,
      322
    ],
    [
      1764810820331.3447,
      520,
      397
    ],
    [
      1764810820372.506,
      880,
      453
    ],
    [
      1764810820414.5867,
      880,
      435
    ],
    [
      1764810820461.814,
      880,
      435
    ],
    [
      1764810820503.801,
      880,
      416
    ],
    [
      1764810820539.5168,
      893,
      435
    ],
    [
      1764810820582.0798,
      893,
      453
    ],
    [
      1764810820617.203,
      893,
      416
    ],
    [
      1764810820651.593,
      893,
      453
    ],
    [
      1764810820692.8489,
      893,
      453
    ],
    [
      1764810820734.2542,
      893,
      416
    ],
    [
      1764810820775.176,
      893,
      416
    ],
    [
      1764810820810.7112,
      893,
      472
    ],
    [
      1764810820845.312,
      905,
      491
    ],
    [
      1764810820887.685,
      905,
      416
    ],
    [
      1764810820928.111,
      893,
      435
    ],
    [
      1764810820963.62,
      893,
      491
    ],
    [
      1764810821005.727,
      893,
      435
    ],
    [
      1764810821047.652,
      905,
      472
    ],
    [
      1764810821082.777,
      893,
      453
    ],
    [
      1764810821116.8718,
      905,
      472
    ],
    [
      1764810821157.887,
      893,
      453
    ],
    [
      1764810821199.3743,
      781,
      435
    ],
    [
      1764810821235.276,
      718,
      435
    ],
    [
      1764810821278.2322,
      706,
      416
    ],
    [
      1764810821320.769,
      706,
      472
    ],
    [
      1764810821354.794,
      694,
      435
    ],
    [
      1764810821397.232,
      706,
      435
    ],
    [
      1764810821439.976,
      706,
      397
    ],
    [
      1764810821475.025,
      694,
      397
    ],
    [
      1764810821509.137,
      694,
      435
    ],
    [
      1764810821551.553,
      694,
      416
    ],
    [
      1764810821587.372,
      694,
      416
    ],
    [
      1764810821621.789,
      706,
      435
    ],
    [
      1764810821658.0967,
      706,
      416
    ],
    [
      1764810821693.0771,
      706,
      378
    ],
    [
      1764810821727.884,
      706,
      416
    ],
    [
      1764810821764.753,
      718,
      472
    ],
    [
      1764810821806.752,
      718,
      435
    ],
    [
      1764810821841.7651,
      718,
      453
    ],
    [
      1764810821875.772,
      718,
      416
    ],
    [
      1764810821918.3848,
      731,
      453
    ],
    [
      1764810821956.5999,
      731,
      435
    ],
    [
      1764810821997.871,
      731,
      435
    ],
    [
      1764810822039.1382,
      743,
      435
    ],
    [
      1764810822073.3828,
      743,
      472
    ],
    [
      1764810822108.628,
      731,
      397
    ],
    [
      1764810822144.372,
      743,
      472
    ],
    [
      1764810822179.046,
      743,
      416
    ],
    [
      1764810822213.294,
      756,
      435
    ],
    [
      1764810822255.157,
      743,
      435
    ],
    [
      1764810822289.8428,
      756,
      435
    ],
    [
      1764810822324.959,
      743,
      435
    ],
    [
      1764810822367.358,
      743,
      416
    ],
    [
      1764810822402.637,
      743,
      453
    ],
    [
      1764810822437.592,
      743,
      416
    ],
    [
      1764810822480.2297,
      743,
      416
    ],
    [
      1764810822527.724,
      968,
      397
    ],
    [
      1764810822563.355,
      1081,
      416
    ],
    [
      1764810822605.7532,
      1169,
      453
    ],
    [
      1764810822646.7478,
      1169,
      472
    ],
    [
      1764810822682.796,
      1169,
      472
    ],
    [
      1764810822716.9258,
      1182,
      491
    ],
    [
      1764810822757.625,
      1182,
      491
    ],
    [
      1764810822798.003,
      1182,
      491
    ],
    [
      1764810822840.158,
      1182,
      491
    ],
    [
      1764810822875.22,
      1194,
      491
    ],
    [
      1764810822917.36,
      1194,
      491
    ],
    [
      1764810822959.1382,
      1194,
      491
    ],
    [
      1764810822992.824,
      1207,
      509
    ],
    [
      1764810823027.503,
      1207,
      509
    ],
    [
      1764810823070.1958,
      1207,
      509
    ],
    [
      1764810823106.5002,
      1220,
      509
    ],
    [
      1764810823141.443,
      1220,
      509
    ],
    [
      1764810823177.133,
      1220,
      528
    ],
    [
      1764810823210.466,
      1220,
      509
    ],
    [
      1764810823253.061,
      1220,
      509
    ],
    [
      1764810823295.737,
      1232,
      509
    ],
    [
      1764810823331.267,
      1232,
      509
    ],
    [
      1764810823373.916,
      1232,
      509
    ],
    [
      1764810823415.2373,
      1106,
      491
    ],
    [
      1764810823450.261,
      831,
      435
    ],
    [
      1764810823485.281,
      831,
      491
    ],
    [
      1764810823521.392,
      831,
      435
    ],
    [
      1764810823564.981,
      831,
      435
    ],
    [
      1764810823606.221,
      818,
      472
    ],
    [
      1764810823647.414,
      831,
      435
    ],
    [
      1764810823688.214,
      831,
      472
    ],
    [
      1764810823723.0452,
      818,
      435
    ],
    [
      1764810823765.824,
      818,
      416
    ],
    [
      1764810823807.636,
      806,
      472
    ],
    [
      1764810823843.0122,
      818,
      435
    ],
    [
      1764810823884.1099,
      806,
      435
    ],
    [
      1764810823924.8372,
      806,
      397
    ],
    [
      1764810823965.475,
      806,
      472
    ],
    [
      1764810824008.5151,
      806,
      435
    ],
    [
      1764810824044.131,
      806,
      435
    ],
    [
      1764810824086.403,
      806,
      453
    ],
    [
      1764810824121.16,
      793,
      472
    ],
    [
      1764810824155.7441,
      806,
      435
    ],
    [
      1764810824197.565,
      793,
      435
    ],
    [
      1764810824238.034,
      793,
      453
    ],
    [
      1764810824274.137,
      793,
      453
    ],
    [
      1764810824309.325,
      781,
      435
    ],
    [
      1764810824349.4248,
      781,
      435
    ],
    [
      1764810824391.422,
      781,
      435
    ],
    [
      1764810824427.9768,
      1043,
      416
    ],
    [
      1764810824470.102,
      1081,
      472
    ],
    [
      1764810824506.722,
      1081,
      453
    ],
    [
      1764810824549.428,
      1119,
      453
    ],
    [
      1764810824589.5132,
      1359,
      491
    ],
    [
      1764810824631.9338,
      1372,
      509
    ],
    [
      1764810824667.414,
      1372,
      509
    ],
    [
      1764810824701.608,
      1372,
      509
    ],
    [
      1764810824738.113,
      1372,
      509
    ],
    [
      1764810824771.7068,
      1384,
      509
    ],
    [
      1764810824813.7942,
      1372,
      509
    ],
    [
      1764810824856.163,
      1372,
      491
    ],
    [
      1764810824891.477,
      1384,
      491
    ],
    [
      1764810824934.497,
      1384,
      491
    ],
    [
      1764810824976.052,
      1372,
      491
    ],
    [
      1764810825012.653,
      1372,
      491
    ],
    [
      1764810825051.832,
      1372,
      491
    ],
    [
      1764810825094.958,
      1372,
      491
    ],
    [
      1764810825129.7761,
      1372,
      491
    ],
    [
      1764810825163.9978,
      1372,
      491
    ],
    [
      1764810825206.161,
      1372,
      453
    ],
    [
      1764810825241.979,
      1372,
      491
    ],
    [
      1764810825275.705,
      1308,
      472
    ],
    [
      1764810825310.8953,
      768,
      378
    ],
    [
      1764810825349.236,
      743,
      435
    ],
    [
      1764810825391.1328,
      743,
      416
    ],
    [
      1764810825426.116,
      743,
      435
    ],
    [
      1764810825460.8628,
      731,
      397
    ],
    [
      1764810825501.496,
      731,
      416
    ],
    [
      1764810825537.178,
      743,
      416
    ],
    [
      1764810825580.9998,
      731,
      416
    ],
    [
      1764810825617.93,
      743,
      378
    ],
    [
      1764810825653.53,
      731,
      397
    ],
    [
      1764810825695.98,
      718,
      397
    ],
    [
      1764810825731.1868,
      731,
      378
    ],
    [
      1764810825775.3652,
      731,
      416
    ],
    [
      1764810825812.563,
      743,
      416
    ],
    [
      1764810825855.4639,
      731,
      416
    ],
    [
      1764810825892.8052,
      743,
      416
    ],
    [
      1764810825941.6692,
      743,
      416
    ],
    [
      1764810825977.913,
      743,
      416
    ],
    [
      1764810826021.286,
      743,
      453
    ],
    [
      1764810826063.562,
      743,
      416
    ],
    [
      1764810826099.5122,
      743,
      416
    ],
    [
      1764810826141.44,
      743,
      435
    ],
    [
      1764810826181.53,
      743,
      435
    ],
    [
      1764810826223.192,
      743,
      435
    ],
    [
      1764810826259.247,
      743,
      435
    ],
    [
      1764810826293.682,
      619,
      491
    ],
    [
      1764810826329.026,
      74,
      416
    ],
    [
      1764810826362.7122,
      0,
      453
    ],
    [
      1764810826397.2,
      25,
      491
    ],
    [
      1764810826438.439,
      25,
      416
    ],
    [
      1764810826475.224,
      25,
      435
    ],
    [
      1764810826517.659,
      25,
      435
    ],
    [
      1764810826559.0068,
      25,
      435
    ],
    [
      1764810826594.3801,
      25,
      435
    ],
    [
      1764810826635.7087,
      37,
      435
    ],
    [
      1764810826678.0679,
      25,
      435
    ],
    [
      1764810826719.084,
      25,
      435
    ],
    [
      1764810826755.5032,
      25,
      435
    ],
    [
      1764810826797.085,
      25,
      435
    ],
    [
      1764810826839.842,
      25,
      416
    ],
    [
      1764810826874.1482,
      25,
      435
    ],
    [
      1764810826908.64,
      25,
      416
    ],
    [
      1764810826950.998,
      25,
      435
    ],
    [
      1764810826986.1409,
      25,
      435
    ],
    [
      1764810827019.918,
      37,
      416
    ],
    [
      1764810827062.145,
      37,
      416
    ],
    [
      1764810827103.4749,
      37,
      416
    ],
    [
      1764810827138.2358,
      37,
      416
    ],
    [
      1764810827181.4048,
      62,
      416
    ],
    [
      1764810827223.5552,
      756,
      435
    ],
    [
      1764810827258.527,
      768,
      472
    ],
    [
      1764810827292.843,
      768,
      472
    ],
    [
      1764810827333.5317,
      768,
      472
    ],
    [
      1764810827375.2861,
      781,
      453
    ],
    [
      1764810827410.4697,
      781,
      453
    ],
    [
      1764810827444.669,
      781,
      378
    ],
    [
      1764810827488.1038,
      793,
      378
    ],
    [
      1764810827523.629,
      768,
      435
    ],
    [
      1764810827564.075,
      756,
      397
    ],
    [
      1764810827605.64,
      756,
      416
    ],
    [
      1764810827647.7173,
      768,
      435
    ],
    [
      1764810827682.9922,
      768,
      416
    ],
    [
      1764810827717.3818,
      781,
      416
    ],
    [
      1764810827754.1492,
      781,
      359
    ],
    [
      1764810827794.963,
      781,
      378
    ],
    [
      1764810827828.928,
      768,
      397
    ],
    [
      1764810827871.657,
      768,
      397
    ],
    [
      1764810827907.352,
      768,
      435
    ],
    [
      1764810827949.7458,
      781,
      435
    ],
    [
      1764810827997.309,
      781,
      416
    ],
    [
      1764810828038.2942,
      781,
      453
    ],
    [
      1764810828079.4548,
      768,
      453
    ],
    [
      1764810828117.16,
      768,
      435
    ],
    [
      1764810828153.6938,
      756,
      435
    ],
    [
      1764810828187.773,
      756,
      453
    ],
    [
      1764810828228.981,
      743,
      435
    ],
    [
      1764810828271.393,
      743,
      453
    ],
    [
      1764810828306.7131,
      743,
      453
    ],
    [
      1764810828349.1687,
      743,
      453
    ],
    [
      1764810828391.6108,
      756,
      453
    ],
    [
      1764810828426.73,
      768,
      453
    ],
    [
      1764810828468.0881,
      1068,
      435
    ],
    [
      1764810828510.18,
      1081,
      491
    ],
    [
      1764810828545.86,
      1081,
      491
    ],
    [
      1764810828581.696,
      1094,
      491
    ],
    [
      1764810828623.3333,
      1106,
      491
    ],
    [
      1764810828658.403,
      1106,
      491
    ],
    [
      1764810828699.409,
      1106,
      491
    ],
    [
      1764810828741.25,
      1106,
      491
    ],
    [
      1764810828776.9521,
      1106,
      472
    ],
    [
      1764810828811.7112,
      1119,
      453
    ],
    [
      1764810828853.985,
      1119,
      472
    ],
    [
      1764810828896.0728,
      1119,
      453
    ],
    [
      1764810828930.077,
      1119,
      453
    ],
    [
      1764810828963.491,
      1119,
      472
    ],
    [
      1764810829006.2202,
      1119,
      472
    ],
    [
      1764810829048.2222,
      1119,
      472
    ],
    [
      1764810829083.872,
      1119,
      491
    ],
    [
      1764810829126.988,
      1119,
      453
    ],
    [
      1764810829160.995,
      1119,
      472
    ],
    [
      1764810829195.689,
      1119,
      472
    ],
    [
      1764810829238.3162,
      1106,
      472
    ],
    [
      1764810829273.4731,
      1106,
      491
    ],
    [
      1764810829308.689,
      1106,
      491
    ],
    [
      1764810829351.6792,
      993,
      435
    ],
    [
      1764810829385.8481,
      756,
      416
    ],
    [
      1764810829420.496,
      743,
      453
    ],
    [
      1764810829463.42,
      743,
      435
    ],
    [
      1764810829498.871,
      743,
      416
    ],
    [
      1764810829542.566,
      743,
      435
    ],
    [
      1764810829583.5771,
      743,
      435
    ],
    [
      1764810829622.551,
      743,
      453
    ],
    [
      1764810829658.719,
      731,
      435
    ],
    [
      1764810829701.628,
      731,
      472
    ],
    [
      1764810829743.5232,
      731,
      472
    ],
    [
      1764810829779.541,
      743,
      472
    ],
    [
      1764810829828.364,
      743,
      472
    ],
    [
      1764810829869.3162,
      731,
      472
    ],
    [
      1764810829911.5642,
      731,
      472
    ],
    [
      1764810829953.603,
      743,
      491
    ],
    [
      1764810829989.2192,
      743,
      491
    ],
    [
      1764810830031.996,
      743,
      472
    ],
    [
      1764810830066.011,
      731,
      472
    ],
    [
      1764810830100.7969,
      731,
      491
    ],
    [
      1764810830143.599,
      731,
      491
    ],
    [
      1764810830180.5872,
      731,
      491
    ],
    [
      1764810830223.5679,
      743,
      491
    ],
    [
      1764810830259.228,
      743,
      491
    ],
    [
      1764810830299.01,
      743,
      491
    ],
    [
      1764810830341.602,
      743,
      472
    ],
    [
      1764810830376.965,
      743,
      472
    ],
    [
      1764810830411.777,
      743,
      491
    ],
    [
      1764810830454.468,
      743,
      491
    ],
    [
      1764810830489.3271,
      743,
      491
    ],
    [
      1764810830536.277,
      743,
      509
    ],
    [
      1764810830571.813,
      1131,
      509
    ],
    [
      1764810830615.1838,
      1156,
      528
    ],
    [
      1764810830649.983,
      1156,
      528
    ],
    [
      1764810830683.687,
      1156,
      528
    ],
    [
      1764810830726.448,
      1169,
      528
    ],
    [
      1764810830767.222,
      1169,
      528
    ],
    [
      1764810830802.1838,
      1384,
      583
    ],
    [
      1764810830836.9238,
      1384,
      583
    ],
    [
      1764810830879.6558,
      1384,
      583
    ],
    [
      1764810830914.208,
      1397,
      583
    ],
    [
      1764810830948.974,
      1384,
      583
    ],
    [
      1764810830989.866,
      1397,
      583
    ],
    [
      1764810831031.529,
      1397,
      583
    ],
    [
      1764810831066.161,
      1384,
      565
    ],
    [
      1764810831100.6238,
      1397,
      565
    ],
    [
      1764810831143.728,
      1397,
      565
    ],
    [
      1764810831178.798,
      1397,
      565
    ],
    [
      1764810831219.945,
      1397,
      565
    ],
    [
      1764810831262.335,
      1397,
      565
    ],
    [
      1764810831297.415,
      1397,
      565
    ],
    [
      1764810831332.809,
      1397,
      565
    ],
    [
      1764810831375.2917,
      1384,
      565
    ],
    [
      1764810831411.712,
      818,
      509
    ],
    [
      1764810831452.4749,
      831,
      509
    ],
    [
      1764810831495.491,
      818,
      509
    ],
    [
      1764810831532.5671,
      818,
      491
    ],
    [
      1764810831569.0762,
      818,
      491
    ],
    [
      1764810831603.982,
      743,
      491
    ],
    [
      1764810831652.979,
      743,
      472
    ],
    [
      1764810831694.2332,
      743,
      491
    ],
    [
      1764810831735.1838,
      743,
      491
    ],
    [
      1764810831771.1208,
      743,
      491
    ],
    [
      1764810831813.558,
      743,
      453
    ],
    [
      1764810831856.458,
      743,
      472
    ],
    [
      1764810831897.543,
      743,
      472
    ],
    [
      1764810831940.843,
      743,
      472
    ],
    [
      1764810831982.548,
      743,
      472
    ],
    [
      1764810832023.396,
      743,
      416
    ],
    [
      1764810832061.867,
      756,
      397
    ],
    [
      1764810832103.411,
      756,
      397
    ],
    [
      1764810832136.7979,
      756,
      416
    ],
    [
      1764810832172.394,
      756,
      472
    ],
    [
      1764810832214.282,
      756,
      453
    ],
    [
      1764810832255.221,
      743,
      378
    ],
    [
      1764810832291.009,
      768,
      397
    ],
    [
      1764810832325.474,
      756,
      435
    ],
    [
      1764810832360.2441,
      756,
      435
    ],
    [
      1764810832395.6218,
      756,
      453
    ],
    [
      1764810832437.727,
      756,
      453
    ],
    [
      1764810832479.9668,
      756,
      472
    ],
    [
      1764810832515.836,
      756,
      453
    ],
    [
      1764810832558.908,
      756,
      491
    ],
    [
      1764810832598.834,
      743,
      472
    ],
    [
      1764810832635.431,
      743,
      453
    ],
    [
      1764810832678.188,
      768,
      491
    ],
    [
      1764810832719.954,
      1144,
      472
    ],
    [
      1764810832756.449,
      1156,
      491
    ],
    [
      1764810832797.1467,
      1156,
      491
    ],
    [
      1764810832840.1821,
      1182,
      491
    ],
    [
      1764810832875.5178,
      1410,
      546
    ],
    [
      1764810832917.8162,
      1410,
      565
    ],
    [
      1764810832959.918,
      1410,
      565
    ],
    [
      1764810832995.325,
      1422,
      546
    ],
    [
      1764810833036.59,
      1422,
      546
    ],
    [
      1764810833078.1628,
      1422,
      546
    ],
    [
      1764810833113.541,
      1422,
      546
    ],
    [
      1764810833148.261,
      1422,
      546
    ],
    [
      1764810833191.4382,
      1422,
      546
    ],
    [
      1764810833226.8213,
      1422,
      546
    ],
    [
      1764810833267.3381,
      1422,
      546
    ],
    [
      1764810833301.6401,
      1207,
      472
    ],
    [
      1764810833343.882,
      831,
      435
    ]
  ]
}