{
  "metadata": {
    "timestamp": "20251206_165106",
    "test_date": "2025-12-06T16:51:06.545320",
    "monitor_width": 1512,
    "monitor_height": 982,
    "total_targets": 12,
    "gap_duration_ms": 200
  },
  "results": {
    "normal_saccade": {
      "total_saccades": 10,
      "valid_saccades": 10,
      "average_latency_ms": 200.5929931640625,
      "average_velocity_deg_per_ms": 0.29220565409338034,
      "average_accuracy_percent": 34.23821148068663,
      "std_latency_ms": 105.31532341964085,
      "std_velocity_deg_per_ms": 0.1562729587078945,
      "std_accuracy_percent": 27.67969734208111
    },
    "antisaccade": {
      "total_trials": 12,
      "error_count": 3,
      "correct_count": 9,
      "error_rate_percent": 25.0
    }
  },
  "normal_saccade_data": [
    {
      "target_index": 0,
      "target_angle_degrees": -10.219654030855498,
      "target_x": 484,
      "target_y": 491,
      "saccade_latency_ms": 224.39404296875,
      "peak_velocity_deg_per_ms": 0.13075884570446386,
      "peak_velocity_deg_per_s": 130.75884570446385,
      "accuracy_percent": 64.24383538867933
    },
    {
      "target_index": 1,
      "target_angle_degrees": -13.259632145341996,
      "target_x": 400,
      "target_y": 491,
      "saccade_latency_ms": 305.8359375,
      "peak_velocity_deg_per_ms": 0.23598180304014182,
      "peak_velocity_deg_per_s": 235.9818030401418,
      "accuracy_percent": 97.76264652138126
    },
    {
      "target_index": 2,
      "target_angle_degrees": 12.63853511917234,
      "target_x": 1094,
      "target_y": 491,
      "saccade_latency_ms": 72.20703125,
      "peak_velocity_deg_per_ms": 0.20945061870227355,
      "peak_velocity_deg_per_s": 209.45061870227354,
      "accuracy_percent": 3.898172321719802
    },
    {
      "target_index": 3,
      "target_angle_degrees": 16.998878898829624,
      "target_x": 1218,
      "target_y": 491,
      "saccade_latency_ms": 235.08203125,
      "peak_velocity_deg_per_ms": 0.1914640126292122,
      "peak_velocity_deg_per_s": 191.4640126292122,
      "accuracy_percent": 33.11241207471832
    },
    {
      "target_index": 4,
      "target_angle_degrees": 27.841876070752527,
      "target_x": 1511,
      "target_y": 491,
      "saccade_latency_ms": 250.24365234375,
      "peak_velocity_deg_per_ms": 0.5963901079288877,
      "peak_velocity_deg_per_s": 596.3901079288877,
      "accuracy_percent": 26.933331126333055
    },
    {
      "target_index": 5,
      "target_angle_degrees": 18.555841476306334,
      "target_x": 1263,
      "target_y": 491,
      "saccade_latency_ms": 364.694091796875,
      "peak_velocity_deg_per_ms": 0.19476717200298513,
      "peak_velocity_deg_per_s": 194.76717200298512,
      "accuracy_percent": 22.83336180438805
    },
    {
      "target_index": 7,
      "target_angle_degrees": 12.862322094349409,
      "target_x": 1101,
      "target_y": 491,
      "saccade_latency_ms": 35.281005859375,
      "peak_velocity_deg_per_ms": 0.093579716344236,
      "peak_velocity_deg_per_s": 93.57971634423599,
      "accuracy_percent": 47.55177304375018
    },
    {
      "target_index": 8,
      "target_angle_degrees": -28.305911999025803,
      "target_x": 0,
      "target_y": 491,
      "saccade_latency_ms": 289.551025390625,
      "peak_velocity_deg_per_ms": 0.46643158084488795,
      "peak_velocity_deg_per_s": 466.43158084488795,
      "accuracy_percent": 19.885382351420184
    },
    {
      "target_index": 9,
      "target_angle_degrees": 22.651719523265946,
      "target_x": 1386,
      "target_y": 491,
      "saccade_latency_ms": 82.099853515625,
      "peak_velocity_deg_per_ms": 0.36831367670272463,
      "peak_velocity_deg_per_s": 368.31367670272465,
      "accuracy_percent": 0.0
    },
    {
      "target_index": 10,
      "target_angle_degrees": -28.663611087824396,
      "target_x": 0,
      "target_y": 491,
      "saccade_latency_ms": 146.541259765625,
      "peak_velocity_deg_per_ms": 0.43491900703399045,
      "peak_velocity_deg_per_s": 434.91900703399045,
      "accuracy_percent": 26.16120017447609
    }
  ],
  "antisaccade_data": [
    {
      "target_index": 0,
      "target_angle_degrees": -17.101309933853265,
      "target_x": 291,
      "target_y": 491,
      "error": false
    },
    {
      "target_index": 1,
      "target_angle_degrees": -6.963194381900911,
      "target_x": 572,
      "target_y": 491,
      "error": false
    },
    {
      "target_index": 2,
      "target_angle_degrees": 7.332605688315217,
      "target_x": 950,
      "target_y": 491,
      "error": false
    },
    {
      "target_index": 3,
      "target_angle_degrees": 14.273623941424699,
      "target_x": 1140,
      "target_y": 491,
      "error": false
    },
    {
      "target_index": 4,
      "target_angle_degrees": -15.77977135321775,
      "target_x": 329,
      "target_y": 491,
      "error": true
    },
    {
      "target_index": 5,
      "target_angle_degrees": 17.426425339879934,
      "target_x": 1230,
      "target_y": 491,
      "error": true
    },
    {
      "target_index": 6,
      "target_angle_degrees": 12.476599322438936,
      "target_x": 1090,
      "target_y": 491,
      "error": false
    },
    {
      "target_index": 7,
      "target_angle_degrees": 8.09076195966049,
      "target_x": 970,
      "target_y": 491,
      "error": false
    },
    {
      "target_index": 8,
      "target_angle_degrees": 11.648309650549201,
      "target_x": 1067,
      "target_y": 491,
      "error": false
    },
    {
      "target_index": 9,
      "target_angle_degrees": 11.751595322035708,
      "target_x": 1070,
      "target_y": 491,
      "error": false
    },
    {
      "target_index": 10,
      "target_angle_degrees": -6.322970102682693,
      "target_x": 589,
      "target_y": 491,
      "error": false
    },
    {
      "target_index": 11,
      "target_angle_degrees": -17.590407932081042,
      "target_x": 277,
      "target_y": 491,
      "error": true
    }
  ],
  "gaze_path": [
    [
      1765057815559.959,
      756,
      491
    ],
    [
      1765057815596.118,
      756,
      491
    ],
    [
      1765057815631.5361,
      756,
      491
    ],
    [
      1765057815673.333,
      756,
      491
    ],
    [
      1765057815708.656,
      756,
      491
    ],
    [
      1765057815748.993,
      756,
      491
    ],
    [
      1765057815784.467,
      756,
      491
    ],
    [
      1765057815819.1638,
      756,
      491
    ],
    [
      1765057815853.426,
      756,
      491
    ],
    [
      1765057815897.32,
      743,
      491
    ],
    [
      1765057815931.193,
      743,
      491
    ],
    [
      1765057815966.266,
      557,
      425
    ],
    [
      1765057815999.69,
      569,
      425
    ],
    [
      1765057816037.5737,
      569,
      425
    ],
    [
      1765057816071.4263,
      569,
      425
    ],
    [
      1765057816107.1182,
      557,
      425
    ],
    [
      1765057816141.8892,
      557,
      425
    ],
    [
      1765057816176.5288,
      557,
      441
    ],
    [
      1765057816212.18,
      557,
      425
    ],
    [
      1765057816255.057,
      557,
      425
    ],
    [
      1765057816291.275,
      557,
      425
    ],
    [
      1765057816324.428,
      557,
      425
    ],
    [
      1765057816358.6738,
      557,
      425
    ],
    [
      1765057816395.4968,
      557,
      425
    ],
    [
      1765057816436.4578,
      557,
      425
    ],
    [
      1765057816478.816,
      694,
      458
    ],
    [
      1765057816511.846,
      855,
      508
    ],
    [
      1765057816548.218,
      855,
      508
    ],
    [
      1765057816582.428,
      843,
      508
    ],
    [
      1765057816625.333,
      843,
      508
    ],
    [
      1765057816659.18,
      843,
      524
    ],
    [
      1765057816693.8848,
      843,
      524
    ],
    [
      1765057816727.8508,
      830,
      524
    ],
    [
      1765057816763.7031,
      830,
      524
    ],
    [
      1765057816798.042,
      830,
      524
    ],
    [
      1765057816841.7302,
      830,
      508
    ],
    [
      1765057816877.998,
      843,
      508
    ],
    [
      1765057816910.8237,
      843,
      508
    ],
    [
      1765057816946.524,
      843,
      508
    ],
    [
      1765057816981.159,
      855,
      508
    ],
    [
      1765057817023.097,
      855,
      508
    ],
    [
      1765057817064.948,
      855,
      508
    ],
    [
      1765057817100.153,
      743,
      475
    ],
    [
      1765057817132.426,
      731,
      475
    ],
    [
      1765057817174.097,
      731,
      475
    ],
    [
      1765057817216.5771,
      731,
      475
    ],
    [
      1765057817252.311,
      731,
      475
    ],
    [
      1765057817286.963,
      731,
      475
    ],
    [
      1765057817324.19,
      731,
      475
    ],
    [
      1765057817356.868,
      731,
      475
    ],
    [
      1765057817390.0808,
      718,
      475
    ],
    [
      1765057817432.566,
      718,
      475
    ],
    [
      1765057817469.868,
      718,
      475
    ],
    [
      1765057817511.936,
      718,
      475
    ],
    [
      1765057817553.3572,
      718,
      458
    ],
    [
      1765057817587.158,
      718,
      441
    ],
    [
      1765057817622.199,
      631,
      425
    ],
    [
      1765057817664.9111,
      607,
      441
    ],
    [
      1765057817700.402,
      607,
      441
    ],
    [
      1765057817734.803,
      607,
      441
    ],
    [
      1765057817771.3643,
      607,
      441
    ],
    [
      1765057817803.9028,
      607,
      441
    ],
    [
      1765057817838.6628,
      607,
      441
    ],
    [
      1765057817880.7148,
      607,
      441
    ],
    [
      1765057817915.7388,
      607,
      441
    ],
    [
      1765057817949.753,
      607,
      441
    ],
    [
      1765057817993.1208,
      607,
      458
    ],
    [
      1765057818033.527,
      607,
      458
    ],
    [
      1765057818066.919,
      607,
      458
    ],
    [
      1765057818101.364,
      607,
      458
    ],
    [
      1765057818144.612,
      607,
      458
    ],
    [
      1765057818180.278,
      607,
      458
    ],
    [
      1765057818222.559,
      607,
      458
    ],
    [
      1765057818262.783,
      607,
      458
    ],
    [
      1765057818304.61,
      607,
      458
    ],
    [
      1765057818340.982,
      656,
      441
    ],
    [
      1765057818382.726,
      756,
      458
    ],
    [
      1765057818418.5269,
      756,
      458
    ],
    [
      1765057818454.54,
      756,
      458
    ],
    [
      1765057818494.272,
      756,
      458
    ],
    [
      1765057818536.719,
      756,
      458
    ],
    [
      1765057818571.99,
      768,
      458
    ],
    [
      1765057818606.4893,
      756,
      458
    ],
    [
      1765057818648.266,
      756,
      458
    ],
    [
      1765057818684.25,
      756,
      458
    ],
    [
      1765057818717.387,
      743,
      458
    ],
    [
      1765057818760.684,
      718,
      458
    ],
    [
      1765057818798.4167,
      718,
      458
    ],
    [
      1765057818840.985,
      718,
      458
    ],
    [
      1765057818876.8481,
      718,
      458
    ],
    [
      1765057818910.8328,
      718,
      458
    ],
    [
      1765057818951.4082,
      718,
      475
    ],
    [
      1765057818993.536,
      718,
      475
    ],
    [
      1765057819028.6392,
      706,
      475
    ],
    [
      1765057819070.577,
      706,
      475
    ],
    [
      1765057819112.9758,
      706,
      475
    ],
    [
      1765057819148.9978,
      718,
      475
    ],
    [
      1765057819181.623,
      718,
      475
    ],
    [
      1765057819224.5068,
      718,
      475
    ],
    [
      1765057819260.0,
      718,
      458
    ],
    [
      1765057819294.4797,
      718,
      458
    ],
    [
      1765057819337.019,
      718,
      458
    ],
    [
      1765057819372.6777,
      718,
      475
    ],
    [
      1765057819405.7368,
      718,
      475
    ],
    [
      1765057819448.7969,
      718,
      475
    ],
    [
      1765057819484.9128,
      718,
      475
    ],
    [
      1765057819526.873,
      718,
      475
    ],
    [
      1765057819563.571,
      718,
      475
    ],
    [
      1765057819597.0718,
      718,
      475
    ],
    [
      1765057819637.587,
      582,
      441
    ],
    [
      1765057819680.689,
      483,
      425
    ],
    [
      1765057819716.4468,
      483,
      425
    ],
    [
      1765057819750.6418,
      483,
      425
    ],
    [
      1765057819786.7761,
      483,
      425
    ],
    [
      1765057819821.087,
      483,
      425
    ],
    [
      1765057819862.092,
      483,
      425
    ],
    [
      1765057819904.853,
      483,
      425
    ],
    [
      1765057819940.844,
      483,
      425
    ],
    [
      1765057819983.4548,
      483,
      425
    ],
    [
      1765057820018.8757,
      483,
      425
    ],
    [
      1765057820053.438,
      483,
      425
    ],
    [
      1765057820094.86,
      483,
      425
    ],
    [
      1765057820128.29,
      718,
      475
    ],
    [
      1765057820164.491,
      718,
      491
    ],
    [
      1765057820206.378,
      718,
      491
    ],
    [
      1765057820248.8389,
      718,
      491
    ],
    [
      1765057820284.755,
      718,
      491
    ],
    [
      1765057820317.065,
      718,
      491
    ],
    [
      1765057820353.915,
      718,
      491
    ],
    [
      1765057820389.497,
      718,
      491
    ],
    [
      1765057820432.727,
      706,
      491
    ],
    [
      1765057820468.352,
      706,
      491
    ],
    [
      1765057820510.453,
      706,
      491
    ],
    [
      1765057820550.2139,
      706,
      508
    ],
    [
      1765057820592.525,
      706,
      491
    ],
    [
      1765057820628.212,
      718,
      491
    ],
    [
      1765057820663.05,
      718,
      491
    ],
    [
      1765057820705.2678,
      718,
      491
    ],
    [
      1765057820740.4302,
      718,
      491
    ],
    [
      1765057820773.3162,
      718,
      491
    ],
    [
      1765057820816.525,
      718,
      491
    ],
    [
      1765057820851.875,
      718,
      491
    ],
    [
      1765057820886.546,
      718,
      491
    ],
    [
      1765057820929.016,
      718,
      491
    ],
    [
      1765057820963.991,
      731,
      491
    ],
    [
      1765057821003.656,
      718,
      491
    ],
    [
      1765057821045.964,
      718,
      491
    ],
    [
      1765057821088.5708,
      718,
      491
    ],
    [
      1765057821123.919,
      718,
      491
    ],
    [
      1765057821157.8728,
      718,
      491
    ],
    [
      1765057821192.3818,
      706,
      491
    ],
    [
      1765057821241.386,
      408,
      408
    ],
    [
      1765057821277.51,
      408,
      425
    ],
    [
      1765057821312.896,
      408,
      425
    ],
    [
      1765057821349.7952,
      408,
      425
    ],
    [
      1765057821386.352,
      396,
      425
    ],
    [
      1765057821420.465,
      396,
      441
    ],
    [
      1765057821461.72,
      396,
      441
    ],
    [
      1765057821495.2332,
      396,
      441
    ],
    [
      1765057821532.5398,
      408,
      425
    ],
    [
      1765057821570.092,
      408,
      425
    ],
    [
      1765057821605.033,
      408,
      425
    ],
    [
      1765057821647.298,
      458,
      425
    ],
    [
      1765057821695.52,
      743,
      508
    ],
    [
      1765057821729.066,
      731,
      508
    ],
    [
      1765057821791.5032,
      731,
      508
    ],
    [
      1765057821841.6362,
      731,
      508
    ],
    [
      1765057821879.313,
      731,
      508
    ],
    [
      1765057821919.531,
      731,
      508
    ],
    [
      1765057821955.1648,
      731,
      508
    ],
    [
      1765057821991.9622,
      731,
      508
    ],
    [
      1765057822028.1401,
      718,
      508
    ],
    [
      1765057822065.611,
      718,
      508
    ],
    [
      1765057822101.811,
      694,
      508
    ],
    [
      1765057822151.25,
      669,
      508
    ],
    [
      1765057822193.4663,
      644,
      491
    ],
    [
      1765057822228.3298,
      619,
      491
    ],
    [
      1765057822263.0222,
      607,
      491
    ],
    [
      1765057822298.748,
      631,
      408
    ],
    [
      1765057822333.3098,
      681,
      308
    ],
    [
      1765057822374.0999,
      669,
      308
    ],
    [
      1765057822410.832,
      656,
      308
    ],
    [
      1765057822444.082,
      656,
      308
    ],
    [
      1765057822478.965,
      644,
      308
    ],
    [
      1765057822515.79,
      644,
      308
    ],
    [
      1765057822551.172,
      644,
      308
    ],
    [
      1765057822588.741,
      743,
      124
    ],
    [
      1765057822627.842,
      743,
      124
    ],
    [
      1765057822663.893,
      731,
      107
    ],
    [
      1765057822699.475,
      731,
      107
    ],
    [
      1765057822736.3433,
      731,
      107
    ],
    [
      1765057822776.543,
      731,
      107
    ],
    [
      1765057822828.939,
      731,
      107
    ],
    [
      1765057822864.194,
      805,
      0
    ],
    [
      1765057822902.1758,
      805,
      0
    ],
    [
      1765057822937.8108,
      793,
      0
    ],
    [
      1765057822971.848,
      793,
      0
    ],
    [
      1765057823008.089,
      706,
      0
    ],
    [
      1765057823062.217,
      507,
      0
    ],
    [
      1765057823097.558,
      507,
      0
    ],
    [
      1765057823131.562,
      520,
      0
    ],
    [
      1765057823172.9973,
      520,
      0
    ],
    [
      1765057823208.791,
      507,
      0
    ],
    [
      1765057823244.462,
      507,
      0
    ],
    [
      1765057823299.553,
      507,
      0
    ],
    [
      1765057823334.124,
      507,
      0
    ],
    [
      1765057823369.206,
      507,
      0
    ],
    [
      1765057823404.238,
      507,
      0
    ],
    [
      1765057823438.545,
      507,
      0
    ],
    [
      1765057823480.0798,
      507,
      0
    ],
    [
      1765057823516.089,
      507,
      0
    ],
    [
      1765057823549.103,
      520,
      0
    ],
    [
      1765057823597.6829,
      507,
      0
    ],
    [
      1765057823639.32,
      507,
      0
    ],
    [
      1765057823675.981,
      607,
      157
    ],
    [
      1765057823709.159,
      607,
      241
    ],
    [
      1765057823749.529,
      607,
      241
    ],
    [
      1765057823784.812,
      594,
      241
    ],
    [
      1765057823820.074,
      594,
      258
    ],
    [
      1765057823854.8547,
      582,
      258
    ],
    [
      1765057823891.0269,
      582,
      241
    ],
    [
      1765057823933.966,
      582,
      241
    ],
    [
      1765057823975.0112,
      520,
      838
    ],
    [
      1765057824017.267,
      446,
      981
    ],
    [
      1765057824052.22,
      433,
      981
    ],
    [
      1765057824085.9202,
      421,
      981
    ],
    [
      1765057824128.4531,
      408,
      981
    ],
    [
      1765057824164.617,
      408,
      981
    ],
    [
      1765057824205.222,
      396,
      981
    ],
    [
      1765057824240.384,
      408,
      981
    ],
    [
      1765057824274.635,
      408,
      981
    ],
    [
      1765057824310.902,
      396,
      921
    ],
    [
      1765057824346.8489,
      483,
      23
    ],
    [
      1765057824379.683,
      446,
      73
    ],
    [
      1765057824421.08,
      446,
      73
    ],
    [
      1765057824456.5708,
      446,
      73
    ],
    [
      1765057824498.2751,
      433,
      56
    ],
    [
      1765057824533.309,
      446,
      56
    ],
    [
      1765057824571.105,
      446,
      56
    ],
    [
      1765057824610.791,
      446,
      56
    ],
    [
      1765057824646.379,
      433,
      56
    ],
    [
      1765057824686.818,
      433,
      56
    ],
    [
      1765057824722.851,
      433,
      56
    ],
    [
      1765057824757.188,
      446,
      56
    ],
    [
      1765057824799.273,
      446,
      56
    ],
    [
      1765057824836.063,
      433,
      56
    ],
    [
      1765057824869.09,
      446,
      56
    ],
    [
      1765057824900.747,
      433,
      56
    ],
    [
      1765057824937.0618,
      433,
      56
    ],
    [
      1765057824974.002,
      955,
      375
    ],
    [
      1765057825017.283,
      980,
      408
    ],
    [
      1765057825051.862,
      980,
      391
    ],
    [
      1765057825086.372,
      980,
      391
    ],
    [
      1765057825118.968,
      992,
      391
    ],
    [
      1765057825155.0378,
      992,
      391
    ],
    [
      1765057825197.665,
      980,
      391
    ],
    [
      1765057825241.081,
      980,
      391
    ],
    [
      1765057825275.748,
      980,
      391
    ],
    [
      1765057825310.2368,
      805,
      275
    ],
    [
      1765057825353.775,
      743,
      241
    ],
    [
      1765057825395.72,
      743,
      241
    ],
    [
      1765057825429.504,
      743,
      241
    ],
    [
      1765057825464.579,
      743,
      241
    ],
    [
      1765057825500.099,
      743,
      241
    ],
    [
      1765057825533.419,
      743,
      224
    ],
    [
      1765057825574.993,
      868,
      375
    ],
    [
      1765057825612.0032,
      1005,
      574
    ],
    [
      1765057825645.0188,
      1005,
      574
    ],
    [
      1765057825686.6372,
      1005,
      574
    ],
    [
      1765057825728.197,
      1005,
      558
    ],
    [
      1765057825763.5059,
      731,
      788
    ],
    [
      1765057825805.343,
      718,
      772
    ],
    [
      1765057825840.8691,
      718,
      772
    ],
    [
      1765057825875.322,
      718,
      772
    ],
    [
      1765057825909.935,
      718,
      772
    ],
    [
      1765057825944.639,
      706,
      772
    ],
    [
      1765057825981.175,
      718,
      755
    ],
    [
      1765057826016.375,
      718,
      755
    ],
    [
      1765057826050.567,
      718,
      755
    ],
    [
      1765057826085.1099,
      718,
      755
    ],
    [
      1765057826128.02,
      706,
      755
    ],
    [
      1765057826165.244,
      681,
      739
    ],
    [
      1765057826199.132,
      669,
      739
    ],
    [
      1765057826241.081,
      669,
      739
    ],
    [
      1765057826274.6292,
      669,
      739
    ],
    [
      1765057826313.65,
      868,
      772
    ],
    [
      1765057826354.822,
      868,
      788
    ],
    [
      1765057826390.702,
      880,
      772
    ],
    [
      1765057826430.5151,
      868,
      772
    ],
    [
      1765057826462.9153,
      1511,
      981
    ],
    [
      1765057826499.703,
      1511,
      981
    ],
    [
      1765057826534.911,
      1511,
      981
    ],
    [
      1765057826576.9392,
      868,
      937
    ],
    [
      1765057826620.33,
      918,
      689
    ],
    [
      1765057826661.9739,
      918,
      722
    ],
    [
      1765057826695.8699,
      918,
      722
    ],
    [
      1765057826731.7078,
      918,
      739
    ],
    [
      1765057826766.889,
      781,
      772
    ],
    [
      1765057826809.132,
      644,
      788
    ],
    [
      1765057826844.647,
      644,
      788
    ],
    [
      1765057826888.635,
      644,
      772
    ],
    [
      1765057826924.785,
      644,
      772
    ],
    [
      1765057826965.2422,
      644,
      788
    ],
    [
      1765057827002.131,
      669,
      739
    ],
    [
      1765057827036.0918,
      669,
      739
    ],
    [
      1765057827072.2827,
      669,
      739
    ],
    [
      1765057827112.133,
      669,
      739
    ],
    [
      1765057827148.439,
      669,
      739
    ],
    [
      1765057827181.081,
      669,
      755
    ],
    [
      1765057827217.548,
      656,
      772
    ],
    [
      1765057827252.0903,
      656,
      772
    ],
    [
      1765057827287.585,
      656,
      772
    ],
    [
      1765057827323.314,
      656,
      772
    ],
    [
      1765057827358.5012,
      656,
      772
    ],
    [
      1765057827401.54,
      656,
      788
    ],
    [
      1765057827441.527,
      656,
      788
    ],
    [
      1765057827477.4248,
      918,
      805
    ],
    [
      1765057827519.3213,
      1055,
      838
    ],
    [
      1765057827554.8843,
      1055,
      838
    ],
    [
      1765057827587.319,
      1055,
      855
    ],
    [
      1765057827629.979,
      1068,
      855
    ],
    [
      1765057827663.497,
      1068,
      855
    ],
    [
      1765057827698.674,
      1068,
      855
    ],
    [
      1765057827733.8318,
      768,
      574
    ],
    [
      1765057827769.805,
      272,
      341
    ],
    [
      1765057827805.1992,
      272,
      358
    ],
    [
      1765057827841.139,
      272,
      358
    ],
    [
      1765057827873.6482,
      272,
      358
    ],
    [
      1765057827907.8828,
      272,
      341
    ],
    [
      1765057827942.06,
      272,
      341
    ],
    [
      1765057827984.964,
      384,
      425
    ],
    [
      1765057828020.185,
      384,
      425
    ],
    [
      1765057828056.5498,
      384,
      425
    ],
    [
      1765057828090.369,
      384,
      408
    ],
    [
      1765057828131.1008,
      396,
      408
    ],
    [
      1765057828174.7852,
      446,
      408
    ],
    [
      1765057828208.645,
      943,
      475
    ],
    [
      1765057828244.723,
      930,
      491
    ],
    [
      1765057828288.9211,
      930,
      491
    ],
    [
      1765057828324.6602,
      930,
      475
    ],
    [
      1765057828361.2192,
      930,
      491
    ],
    [
      1765057828397.609,
      930,
      475
    ],
    [
      1765057828432.665,
      930,
      475
    ],
    [
      1765057828467.386,
      930,
      475
    ],
    [
      1765057828510.117,
      930,
      475
    ],
    [
      1765057828551.281,
      930,
      475
    ],
    [
      1765057828586.604,
      930,
      475
    ],
    [
      1765057828622.029,
      930,
      475
    ],
    [
      1765057828656.1978,
      930,
      475
    ],
    [
      1765057828691.021,
      1093,
      805
    ],
    [
      1765057828725.433,
      1080,
      838
    ],
    [
      1765057828774.7688,
      1080,
      821
    ],
    [
      1765057828811.204,
      1068,
      821
    ],
    [
      1765057828845.6042,
      1068,
      821
    ],
    [
      1765057828880.251,
      1068,
      821
    ],
    [
      1765057828916.5283,
      1068,
      821
    ],
    [
      1765057828950.766,
      1068,
      821
    ],
    [
      1765057828987.0488,
      1068,
      821
    ],
    [
      1765057829020.73,
      1068,
      821
    ],
    [
      1765057829056.8398,
      1017,
      821
    ],
    [
      1765057829091.5251,
      843,
      772
    ],
    [
      1765057829134.451,
      843,
      772
    ],
    [
      1765057829168.4648,
      830,
      772
    ],
    [
      1765057829204.3308,
      830,
      772
    ],
    [
      1765057829237.0352,
      830,
      772
    ],
    [
      1765057829273.45,
      830,
      772
    ],
    [
      1765057829313.312,
      830,
      772
    ],
    [
      1765057829348.593,
      830,
      772
    ],
    [
      1765057829384.192,
      918,
      772
    ],
    [
      1765057829426.332,
      918,
      772
    ],
    [
      1765057829460.0488,
      918,
      772
    ],
    [
      1765057829493.531,
      918,
      772
    ],
    [
      1765057829538.5862,
      918,
      755
    ],
    [
      1765057829573.903,
      918,
      772
    ],
    [
      1765057829609.666,
      918,
      772
    ],
    [
      1765057829645.5823,
      893,
      772
    ],
    [
      1765057829685.243,
      818,
      755
    ],
    [
      1765057829728.239,
      818,
      755
    ],
    [
      1765057829764.8,
      830,
      755
    ],
    [
      1765057829798.2039,
      818,
      755
    ],
    [
      1765057829835.413,
      818,
      755
    ],
    [
      1765057829875.5178,
      818,
      755
    ],
    [
      1765057829917.0188,
      818,
      755
    ],
    [
      1765057829951.406,
      818,
      755
    ],
    [
      1765057829987.0159,
      830,
      739
    ],
    [
      1765057830020.532,
      918,
      772
    ],
    [
      1765057830057.2998,
      918,
      772
    ],
    [
      1765057830090.0103,
      918,
      772
    ],
    [
      1765057830126.178,
      918,
      755
    ],
    [
      1765057830167.068,
      918,
      755
    ],
    [
      1765057830208.55,
      918,
      755
    ],
    [
      1765057830243.9922,
      918,
      755
    ],
    [
      1765057830277.3481,
      918,
      755
    ],
    [
      1765057830314.322,
      918,
      755
    ],
    [
      1765057830353.8518,
      1080,
      805
    ],
    [
      1765057830387.584,
      1068,
      805
    ],
    [
      1765057830421.555,
      1068,
      805
    ],
    [
      1765057830456.6191,
      1068,
      805
    ],
    [
      1765057830493.1772,
      607,
      755
    ],
    [
      1765057830529.451,
      607,
      755
    ],
    [
      1765057830564.207,
      594,
      755
    ],
    [
      1765057830605.04,
      594,
      755
    ],
    [
      1765057830639.559,
      594,
      755
    ],
    [
      1765057830676.061,
      594,
      755
    ],
    [
      1765057830711.7078,
      594,
      755
    ],
    [
      1765057830754.1812,
      594,
      755
    ],
    [
      1765057830789.393,
      594,
      755
    ],
    [
      1765057830831.369,
      594,
      772
    ],
    [
      1765057830873.8452,
      594,
      755
    ],
    [
      1765057830912.4429,
      520,
      524
    ],
    [
      1765057830949.0208,
      495,
      524
    ],
    [
      1765057830992.278,
      495,
      524
    ],
    [
      1765057831033.566,
      495,
      524
    ],
    [
      1765057831072.9412,
      408,
      425
    ],
    [
      1765057831109.16,
      285,
      341
    ],
    [
      1765057831142.584,
      272,
      341
    ],
    [
      1765057831185.203,
      272,
      341
    ],
    [
      1765057831221.5413,
      272,
      341
    ],
    [
      1765057831254.71,
      285,
      341
    ],
    [
      1765057831287.582,
      272,
      341
    ],
    [
      1765057831325.782,
      285,
      341
    ],
    [
      1765057831361.596,
      384,
      0
    ],
    [
      1765057831401.9849,
      371,
      0
    ],
    [
      1765057831438.2651,
      359,
      0
    ],
    [
      1765057831474.7432,
      359,
      0
    ],
    [
      1765057831521.675,
      359,
      0
    ],
    [
      1765057831556.843,
      371,
      0
    ],
    [
      1765057831598.041,
      756,
      141
    ],
    [
      1765057831631.957,
      743,
      141
    ],
    [
      1765057831673.987,
      743,
      141
    ],
    [
      1765057831719.069,
      743,
      141
    ],
    [
      1765057831759.25,
      756,
      141
    ],
    [
      1765057831792.803,
      793,
      157
    ],
    [
      1765057831829.4102,
      1243,
      375
    ],
    [
      1765057831863.5251,
      1231,
      375
    ],
    [
      1765057831901.0662,
      1231,
      375
    ],
    [
      1765057831935.853,
      1231,
      375
    ],
    [
      1765057831976.9822,
      1243,
      375
    ],
    [
      1765057832011.965,
      1243,
      375
    ],
    [
      1765057832045.666,
      1243,
      375
    ],
    [
      1765057832080.4321,
      1256,
      375
    ],
    [
      1765057832116.718,
      1256,
      358
    ],
    [
      1765057832159.956,
      1269,
      358
    ],
    [
      1765057832206.846,
      1269,
      358
    ],
    [
      1765057832249.4368,
      1256,
      358
    ],
    [
      1765057832284.9531,
      1256,
      358
    ],
    [
      1765057832318.295,
      1256,
      358
    ],
    [
      1765057832355.889,
      1294,
      358
    ],
    [
      1765057832389.7732,
      1307,
      375
    ],
    [
      1765057832431.7498,
      1319,
      375
    ],
    [
      1765057832472.778,
      1319,
      375
    ],
    [
      1765057832514.496,
      1319,
      375
    ],
    [
      1765057832549.565,
      1319,
      375
    ],
    [
      1765057832585.8108,
      1319,
      375
    ],
    [
      1765057832620.153,
      1319,
      375
    ],
    [
      1765057832662.936,
      1319,
      375
    ],
    [
      1765057832703.822,
      1319,
      375
    ],
    [
      1765057832740.993,
      1332,
      375
    ],
    [
      1765057832782.1838,
      1332,
      375
    ],
    [
      1765057832816.992,
      1332,
      375
    ],
    [
      1765057832852.124,
      1332,
      375
    ],
    [
      1765057832885.885,
      1332,
      375
    ],
    [
      1765057832928.725,
      1332,
      375
    ],
    [
      1765057832966.25,
      955,
      607
    ],
    [
      1765057833006.0068,
      830,
      722
    ],
    [
      1765057833043.148,
      818,
      722
    ],
    [
      1765057833083.512,
      818,
      722
    ],
    [
      1765057833117.6902,
      818,
      722
    ],
    [
      1765057833161.043,
      818,
      722
    ],
    [
      1765057833199.83,
      818,
      722
    ],
    [
      1765057833238.418,
      818,
      722
    ],
    [
      1765057833285.486,
      830,
      722
    ],
    [
      1765057833324.4841,
      880,
      772
    ],
    [
      1765057833369.275,
      868,
      755
    ],
    [
      1765057833405.01,
      868,
      755
    ],
    [
      1765057833447.7717,
      855,
      755
    ],
    [
      1765057833485.6692,
      843,
      755
    ],
    [
      1765057833526.253,
      830,
      755
    ],
    [
      1765057833562.279,
      830,
      739
    ],
    [
      1765057833597.847,
      756,
      739
    ],
    [
      1765057833638.698,
      743,
      739
    ],
    [
      1765057833675.325,
      731,
      739
    ],
    [
      1765057833713.741,
      731,
      739
    ],
    [
      1765057833751.366,
      706,
      739
    ],
    [
      1765057833798.301,
      694,
      739
    ],
    [
      1765057833834.571,
      694,
      739
    ],
    [
      1765057833869.098,
      681,
      739
    ],
    [
      1765057833903.755,
      669,
      739
    ],
    [
      1765057833946.414,
      644,
      722
    ],
    [
      1765057833982.6392,
      631,
      722
    ],
    [
      1765057834032.188,
      631,
      739
    ],
    [
      1765057834073.7268,
      631,
      739
    ],
    [
      1765057834109.119,
      631,
      739
    ],
    [
      1765057834142.626,
      644,
      673
    ],
    [
      1765057834179.9949,
      644,
      689
    ],
    [
      1765057834214.88,
      644,
      689
    ],
    [
      1765057834264.562,
      631,
      689
    ],
    [
      1765057834306.075,
      557,
      640
    ],
    [
      1765057834342.1838,
      433,
      607
    ],
    [
      1765057834377.6929,
      433,
      607
    ],
    [
      1765057834413.1838,
      433,
      607
    ],
    [
      1765057834448.5,
      421,
      607
    ],
    [
      1765057834483.2817,
      272,
      241
    ],
    [
      1765057834526.402,
      235,
      241
    ],
    [
      1765057834560.694,
      235,
      241
    ],
    [
      1765057834596.4602,
      223,
      241
    ],
    [
      1765057834630.463,
      223,
      241
    ],
    [
      1765057834665.566,
      223,
      241
    ],
    [
      1765057834707.5742,
      235,
      241
    ],
    [
      1765057834740.181,
      235,
      241
    ],
    [
      1765057834782.474,
      223,
      241
    ],
    [
      1765057834817.7932,
      235,
      241
    ],
    [
      1765057839858.0107,
      756,
      491
    ],
    [
      1765057839901.112,
      756,
      491
    ],
    [
      1765057839933.779,
      756,
      491
    ],
    [
      1765057839974.272,
      756,
      491
    ],
    [
      1765057840010.498,
      855,
      558
    ],
    [
      1765057840044.4531,
      843,
      558
    ],
    [
      1765057840086.782,
      843,
      558
    ],
    [
      1765057840128.0051,
      644,
      889
    ],
    [
      1765057840163.798,
      631,
      889
    ],
    [
      1765057840197.9949,
      619,
      889
    ],
    [
      1765057840233.5051,
      619,
      889
    ],
    [
      1765057840277.075,
      619,
      889
    ],
    [
      1765057840312.577,
      619,
      889
    ],
    [
      1765057840348.264,
      606,
      889
    ],
    [
      1765057840382.036,
      544,
      873
    ],
    [
      1765057840431.388,
      532,
      873
    ],
    [
      1765057840465.6118,
      532,
      873
    ],
    [
      1765057840500.6877,
      532,
      873
    ],
    [
      1765057840536.29,
      532,
      873
    ],
    [
      1765057840571.705,
      532,
      873
    ],
    [
      1765057840607.765,
      606,
      889
    ],
    [
      1765057840642.251,
      606,
      889
    ],
    [
      1765057840676.586,
      606,
      889
    ],
    [
      1765057840712.296,
      606,
      889
    ],
    [
      1765057840759.4722,
      606,
      873
    ],
    [
      1765057840793.49,
      681,
      889
    ],
    [
      1765057840829.4949,
      756,
      906
    ],
    [
      1765057840864.324,
      756,
      906
    ],
    [
      1765057840904.829,
      756,
      906
    ],
    [
      1765057840940.825,
      756,
      906
    ],
    [
      1765057840982.803,
      756,
      906
    ],
    [
      1765057841025.28,
      756,
      906
    ],
    [
      1765057841060.163,
      756,
      906
    ],
    [
      1765057841096.4758,
      756,
      906
    ],
    [
      1765057841142.3481,
      756,
      906
    ],
    [
      1765057841184.983,
      718,
      906
    ],
    [
      1765057841221.063,
      718,
      906
    ],
    [
      1765057841261.8281,
      706,
      906
    ],
    [
      1765057841303.5771,
      706,
      906
    ],
    [
      1765057841345.144,
      706,
      906
    ],
    [
      1765057841381.778,
      818,
      906
    ],
    [
      1765057841417.212,
      806,
      906
    ],
    [
      1765057841452.6829,
      806,
      906
    ],
    [
      1765057841488.0781,
      806,
      906
    ],
    [
      1765057841524.533,
      806,
      906
    ],
    [
      1765057841558.899,
      806,
      906
    ],
    [
      1765057841598.83,
      806,
      906
    ],
    [
      1765057841641.658,
      793,
      906
    ],
    [
      1765057841677.554,
      793,
      906
    ],
    [
      1765057841712.524,
      793,
      889
    ],
    [
      1765057841749.011,
      968,
      939
    ],
    [
      1765057841783.453,
      956,
      939
    ],
    [
      1765057841815.853,
      956,
      939
    ],
    [
      1765057841852.368,
      956,
      922
    ],
    [
      1765057841886.3372,
      956,
      922
    ],
    [
      1765057841928.957,
      956,
      922
    ],
    [
      1765057841963.831,
      956,
      922
    ],
    [
      1765057841998.2732,
      943,
      906
    ],
    [
      1765057842031.322,
      893,
      906
    ],
    [
      1765057842067.1611,
      905,
      889
    ],
    [
      1765057842101.712,
      905,
      873
    ],
    [
      1765057842142.832,
      905,
      840
    ],
    [
      1765057842176.242,
      918,
      807
    ],
    [
      1765057842214.082,
      931,
      758
    ],
    [
      1765057842253.845,
      931,
      741
    ],
    [
      1765057842295.969,
      495,
      724
    ],
    [
      1765057842336.853,
      482,
      741
    ],
    [
      1765057842373.559,
      482,
      741
    ],
    [
      1765057842417.821,
      482,
      741
    ],
    [
      1765057842453.7192,
      482,
      741
    ],
    [
      1765057842493.5833,
      470,
      741
    ],
    [
      1765057842528.105,
      470,
      758
    ],
    [
      1765057842563.263,
      519,
      758
    ],
    [
      1765057842596.8718,
      544,
      758
    ],
    [
      1765057842631.693,
      544,
      774
    ],
    [
      1765057842669.137,
      532,
      774
    ],
    [
      1765057842709.836,
      831,
      791
    ],
    [
      1765057842743.314,
      956,
      807
    ],
    [
      1765057842780.9548,
      956,
      824
    ],
    [
      1765057842816.854,
      956,
      824
    ],
    [
      1765057842852.353,
      956,
      824
    ],
    [
      1765057842886.465,
      956,
      824
    ],
    [
      1765057842923.372,
      968,
      824
    ],
    [
      1765057842961.104,
      968,
      824
    ],
    [
      1765057842997.159,
      918,
      791
    ],
    [
      1765057843029.794,
      905,
      774
    ],
    [
      1765057843073.844,
      893,
      774
    ],
    [
      1765057843108.8518,
      743,
      256
    ],
    [
      1765057843141.491,
      718,
      273
    ],
    [
      1765057843174.81,
      706,
      273
    ],
    [
      1765057843217.232,
      693,
      273
    ],
    [
      1765057843252.549,
      693,
      256
    ],
    [
      1765057843294.843,
      693,
      256
    ],
    [
      1765057843336.122,
      606,
      206
    ],
    [
      1765057843372.131,
      569,
      206
    ],
    [
      1765057843405.061,
      569,
      206
    ],
    [
      1765057843439.1611,
      569,
      189
    ],
    [
      1765057843476.215,
      569,
      189
    ],
    [
      1765057843511.497,
      569,
      189
    ],
    [
      1765057843547.8552,
      519,
      591
    ],
    [
      1765057843580.6838,
      507,
      691
    ],
    [
      1765057843619.0632,
      507,
      691
    ],
    [
      1765057843654.4548,
      507,
      675
    ],
    [
      1765057843698.2231,
      495,
      675
    ],
    [
      1765057843733.668,
      495,
      675
    ],
    [
      1765057843768.7822,
      495,
      675
    ],
    [
      1765057843806.1912,
      544,
      741
    ],
    [
      1765057843855.4229,
      569,
      758
    ],
    [
      1765057843895.352,
      569,
      758
    ],
    [
      1765057843931.2893,
      569,
      741
    ],
    [
      1765057843964.8188,
      569,
      758
    ],
    [
      1765057844000.49,
      557,
      741
    ],
    [
      1765057844036.509,
      557,
      741
    ],
    [
      1765057844070.9163,
      557,
      741
    ],
    [
      1765057844104.459,
      557,
      741
    ],
    [
      1765057844140.356,
      557,
      741
    ],
    [
      1765057844175.424,
      743,
      857
    ],
    [
      1765057844215.658,
      731,
      857
    ],
    [
      1765057844252.7139,
      731,
      857
    ],
    [
      1765057844286.819,
      731,
      857
    ],
    [
      1765057844327.8,
      731,
      857
    ],
    [
      1765057844362.971,
      731,
      857
    ],
    [
      1765057844397.417,
      731,
      857
    ],
    [
      1765057844430.954,
      731,
      857
    ],
    [
      1765057844468.0361,
      731,
      857
    ],
    [
      1765057844503.4348,
      693,
      840
    ],
    [
      1765057844545.6692,
      693,
      840
    ],
    [
      1765057844580.1433,
      693,
      857
    ],
    [
      1765057844614.78,
      693,
      840
    ],
    [
      1765057844657.5461,
      693,
      840
    ],
    [
      1765057844696.8809,
      693,
      840
    ],
    [
      1765057844731.6648,
      693,
      840
    ],
    [
      1765057844773.752,
      693,
      840
    ],
    [
      1765057844806.851,
      693,
      824
    ],
    [
      1765057844841.6572,
      706,
      824
    ],
    [
      1765057844877.191,
      843,
      840
    ],
    [
      1765057844910.33,
      931,
      857
    ],
    [
      1765057844953.166,
      918,
      857
    ],
    [
      1765057844997.203,
      931,
      840
    ],
    [
      1765057845032.793,
      931,
      840
    ],
    [
      1765057845069.767,
      931,
      840
    ],
    [
      1765057845105.1143,
      918,
      840
    ],
    [
      1765057845139.7288,
      918,
      840
    ],
    [
      1765057845174.0571,
      918,
      840
    ],
    [
      1765057845216.5981,
      918,
      840
    ],
    [
      1765057845250.278,
      918,
      840
    ],
    [
      1765057845283.2341,
      893,
      807
    ],
    [
      1765057845320.43,
      893,
      807
    ],
    [
      1765057845356.3608,
      893,
      807
    ],
    [
      1765057845390.3308,
      918,
      758
    ],
    [
      1765057845427.415,
      943,
      758
    ],
    [
      1765057845460.9658,
      943,
      758
    ],
    [
      1765057845496.0552,
      943,
      758
    ],
    [
      1765057845532.7449,
      931,
      758
    ],
    [
      1765057845576.0598,
      931,
      758
    ],
    [
      1765057845611.932,
      931,
      758
    ],
    [
      1765057845645.387,
      931,
      758
    ],
    [
      1765057845686.269,
      931,
      758
    ],
    [
      1765057845720.527,
      893,
      741
    ],
    [
      1765057845762.5688,
      880,
      741
    ],
    [
      1765057845798.2888,
      880,
      741
    ],
    [
      1765057845841.9998,
      880,
      741
    ],
    [
      1765057845876.246,
      880,
      741
    ],
    [
      1765057845909.1892,
      880,
      741
    ],
    [
      1765057845952.78,
      880,
      741
    ],
    [
      1765057845988.6348,
      880,
      741
    ],
    [
      1765057846023.831,
      880,
      741
    ],
    [
      1765057846060.194,
      880,
      741
    ],
    [
      1765057846103.05,
      905,
      840
    ],
    [
      1765057846142.304,
      893,
      840
    ],
    [
      1765057846176.585,
      893,
      840
    ],
    [
      1765057846213.674,
      893,
      840
    ],
    [
      1765057846249.0308,
      893,
      840
    ],
    [
      1765057846282.86,
      893,
      840
    ],
    [
      1765057846318.209,
      893,
      840
    ],
    [
      1765057846352.172,
      893,
      840
    ],
    [
      1765057846387.463,
      718,
      625
    ],
    [
      1765057846421.797,
      482,
      206
    ],
    [
      1765057846464.02,
      321,
      138
    ],
    [
      1765057846504.92,
      309,
      155
    ],
    [
      1765057846541.358,
      296,
      172
    ],
    [
      1765057846574.434,
      296,
      172
    ],
    [
      1765057846607.6082,
      296,
      155
    ],
    [
      1765057846644.022,
      296,
      155
    ],
    [
      1765057846677.6199,
      296,
      155
    ],
    [
      1765057846720.291,
      160,
      324
    ],
    [
      1765057846761.302,
      148,
      307
    ],
    [
      1765057846797.683,
      148,
      307
    ],
    [
      1765057846837.2568,
      148,
      307
    ],
    [
      1765057846871.2268,
      160,
      307
    ],
    [
      1765057846908.4648,
      334,
      273
    ],
    [
      1765057846942.2588,
      781,
      307
    ],
    [
      1765057846985.895,
      781,
      307
    ],
    [
      1765057847020.6133,
      781,
      307
    ],
    [
      1765057847053.3818,
      781,
      307
    ],
    [
      1765057847096.5728,
      781,
      307
    ],
    [
      1765057847132.4019,
      781,
      307
    ],
    [
      1765057847167.291,
      781,
      307
    ],
    [
      1765057847203.223,
      793,
      307
    ],
    [
      1765057847237.7542,
      880,
      608
    ],
    [
      1765057847271.9878,
      880,
      922
    ],
    [
      1765057847305.092,
      868,
      922
    ],
    [
      1765057847350.2458,
      868,
      922
    ],
    [
      1765057847387.444,
      868,
      922
    ],
    [
      1765057847421.007,
      905,
      889
    ],
    [
      1765057847456.0693,
      905,
      889
    ],
    [
      1765057847490.399,
      905,
      889
    ],
    [
      1765057847524.074,
      893,
      889
    ],
    [
      1765057847565.471,
      893,
      889
    ],
    [
      1765057847599.6667,
      706,
      840
    ],
    [
      1765057847637.44,
      669,
      840
    ],
    [
      1765057847681.535,
      669,
      840
    ],
    [
      1765057847717.955,
      669,
      840
    ],
    [
      1765057847750.904,
      669,
      840
    ],
    [
      1765057847785.449,
      669,
      840
    ],
    [
      1765057847820.93,
      669,
      840
    ],
    [
      1765057847855.546,
      669,
      840
    ],
    [
      1765057847893.086,
      669,
      840
    ],
    [
      1765057847927.239,
      669,
      824
    ],
    [
      1765057847967.4182,
      681,
      981
    ],
    [
      1765057848005.7139,
      1511,
      981
    ],
    [
      1765057848044.8499,
      1296,
      981
    ],
    [
      1765057848087.913,
      756,
      724
    ],
    [
      1765057848122.643,
      743,
      724
    ],
    [
      1765057848159.9019,
      743,
      741
    ],
    [
      1765057848200.874,
      743,
      758
    ],
    [
      1765057848241.891,
      743,
      758
    ],
    [
      1765057848275.668,
      743,
      774
    ],
    [
      1765057848314.625,
      743,
      758
    ],
    [
      1765057848348.786,
      681,
      774
    ],
    [
      1765057848382.5227,
      656,
      807
    ],
    [
      1765057848431.767,
      656,
      791
    ],
    [
      1765057848468.1921,
      656,
      791
    ],
    [
      1765057848501.487,
      656,
      791
    ],
    [
      1765057848544.7148,
      669,
      791
    ],
    [
      1765057848579.9749,
      669,
      791
    ],
    [
      1765057848616.021,
      669,
      791
    ],
    [
      1765057848649.612,
      669,
      791
    ],
    [
      1765057848689.4111,
      669,
      791
    ],
    [
      1765057848725.5571,
      669,
      791
    ],
    [
      1765057848760.267,
      718,
      758
    ],
    [
      1765057848796.261,
      718,
      758
    ],
    [
      1765057848830.9573,
      731,
      758
    ],
    [
      1765057848873.6472,
      731,
      774
    ],
    [
      1765057848913.155,
      731,
      774
    ],
    [
      1765057848946.767,
      731,
      774
    ],
    [
      1765057848982.722,
      905,
      824
    ],
    [
      1765057849023.138,
      893,
      824
    ],
    [
      1765057849057.7212,
      893,
      824
    ],
    [
      1765057849093.161,
      893,
      840
    ],
    [
      1765057849134.665,
      893,
      840
    ],
    [
      1765057849176.4521,
      893,
      857
    ],
    [
      1765057849212.97,
      893,
      857
    ],
    [
      1765057849247.0698,
      806,
      508
    ],
    [
      1765057849289.8079,
      781,
      357
    ],
    [
      1765057849326.83,
      768,
      357
    ],
    [
      1765057849372.8389,
      768,
      357
    ],
    [
      1765057849414.481,
      768,
      357
    ],
    [
      1765057849449.291,
      768,
      341
    ],
    [
      1765057849484.5737,
      768,
      341
    ],
    [
      1765057849527.91,
      768,
      341
    ],
    [
      1765057849567.103,
      793,
      374
    ],
    [
      1765057849609.459,
      793,
      408
    ],
    [
      1765057849654.6838,
      793,
      391
    ],
    [
      1765057849694.7021,
      793,
      391
    ],
    [
      1765057849737.094,
      793,
      391
    ],
    [
      1765057849771.03,
      793,
      391
    ],
    [
      1765057849806.026,
      793,
      391
    ],
    [
      1765057849846.8179,
      781,
      391
    ],
    [
      1765057849888.612,
      855,
      391
    ],
    [
      1765057849924.8408,
      880,
      408
    ],
    [
      1765057849958.169,
      880,
      408
    ],
    [
      1765057850001.9011,
      880,
      408
    ],
    [
      1765057850034.709,
      880,
      408
    ],
    [
      1765057850068.992,
      880,
      408
    ],
    [
      1765057850106.0059,
      880,
      408
    ],
    [
      1765057850140.958,
      880,
      408
    ],
    [
      1765057850174.92,
      880,
      408
    ],
    [
      1765057850211.6038,
      880,
      408
    ],
    [
      1765057850251.5352,
      868,
      408
    ],
    [
      1765057850287.0579,
      868,
      408
    ],
    [
      1765057850329.945,
      855,
      408
    ],
    [
      1765057850366.157,
      843,
      408
    ],
    [
      1765057850408.618,
      831,
      408
    ],
    [
      1765057850444.8918,
      781,
      424
    ],
    [
      1765057850485.5007,
      693,
      441
    ],
    [
      1765057850521.496,
      582,
      441
    ],
    [
      1765057850556.687,
      507,
      441
    ],
    [
      1765057850591.389,
      457,
      424
    ],
    [
      1765057850626.3271,
      433,
      408
    ],
    [
      1765057850662.271,
      445,
      408
    ],
    [
      1765057850697.133,
      470,
      408
    ],
    [
      1765057850731.6301,
      519,
      408
    ],
    [
      1765057850767.3289,
      582,
      408
    ],
    [
      1765057850805.43,
      669,
      424
    ],
    [
      1765057850839.175,
      743,
      424
    ],
    [
      1765057850877.98,
      843,
      441
    ],
    [
      1765057850914.208,
      918,
      441
    ],
    [
      1765057850947.7583,
      880,
      408
    ],
    [
      1765057850981.3892,
      956,
      424
    ],
    [
      1765057851022.409,
      1031,
      441
    ],
    [
      1765057851058.86,
      1119,
      458
    ],
    [
      1765057851092.964,
      1169,
      458
    ],
    [
      1765057851127.267,
      1157,
      675
    ],
    [
      1765057851168.1301,
      1131,
      922
    ],
    [
      1765057851211.17,
      1131,
      939
    ],
    [
      1765057851252.778,
      1119,
      939
    ],
    [
      1765057851295.625,
      1106,
      922
    ],
    [
      1765057851335.9858,
      1081,
      922
    ],
    [
      1765057851371.8801,
      1069,
      906
    ],
    [
      1765057851405.149,
      1056,
      906
    ],
    [
      1765057851448.041,
      1182,
      541
    ],
    [
      1765057851481.9,
      1144,
      525
    ],
    [
      1765057851517.228,
      1043,
      491
    ],
    [
      1765057851551.9192,
      905,
      491
    ],
    [
      1765057851585.521,
      743,
      475
    ],
    [
      1765057851625.194,
      582,
      458
    ],
    [
      1765057851660.7659,
      433,
      441
    ],
    [
      1765057851702.136,
      321,
      408
    ],
    [
      1765057851744.884,
      272,
      391
    ],
    [
      1765057851780.8052,
      259,
      391
    ],
    [
      1765057851816.0342,
      272,
      391
    ],
    [
      1765057851849.8098,
      173,
      290
    ],
    [
      1765057851885.3708,
      197,
      273
    ],
    [
      1765057851928.8079,
      222,
      273
    ],
    [
      1765057851968.6711,
      210,
      290
    ],
    [
      1765057852004.816,
      210,
      290
    ],
    [
      1765057852039.25,
      222,
      307
    ],
    [
      1765057852088.185,
      272,
      324
    ],
    [
      1765057852124.2559,
      395,
      341
    ],
    [
      1765057852158.179,
      582,
      873
    ],
    [
      1765057852192.2869,
      706,
      873
    ],
    [
      1765057852229.145,
      855,
      889
    ],
    [
      1765057852263.9182,
      943,
      906
    ],
    [
      1765057852312.788,
      1018,
      922
    ],
    [
      1765057852348.4868,
      1056,
      939
    ],
    [
      1765057852383.015,
      1056,
      922
    ],
    [
      1765057852416.5398,
      1056,
      922
    ],
    [
      1765057852453.429,
      1031,
      922
    ],
    [
      1765057852488.966,
      1018,
      922
    ],
    [
      1765057852525.212,
      993,
      774
    ],
    [
      1765057852565.45,
      1056,
      525
    ],
    [
      1765057852606.187,
      1031,
      525
    ],
    [
      1765057852643.502,
      1018,
      525
    ],
    [
      1765057852677.6472,
      1006,
      525
    ],
    [
      1765057852720.5708,
      993,
      508
    ],
    [
      1765057852762.118,
      993,
      508
    ],
    [
      1765057852794.364,
      993,
      508
    ],
    [
      1765057852831.1438,
      1069,
      441
    ],
    [
      1765057852865.5059,
      1056,
      458
    ],
    [
      1765057852901.7798,
      1056,
      458
    ],
    [
      1765057852945.3042,
      1043,
      458
    ],
    [
      1765057852992.373,
      1043,
      458
    ],
    [
      1765057853028.1868,
      1056,
      441
    ],
    [
      1765057853071.0342,
      1056,
      441
    ],
    [
      1765057853112.0598,
      1056,
      424
    ],
    [
      1765057853148.179,
      1006,
      408
    ],
    [
      1765057853181.751,
      931,
      391
    ],
    [
      1765057853222.785,
      831,
      391
    ],
    [
      1765057853258.8,
      718,
      357
    ],
    [
      1765057853292.265,
      644,
      357
    ],
    [
      1765057853336.283,
      594,
      341
    ],
    [
      1765057853372.212,
      557,
      341
    ],
    [
      1765057853414.514,
      519,
      341
    ],
    [
      1765057853455.195,
      482,
      341
    ],
    [
      1765057853497.098,
      457,
      341
    ],
    [
      1765057853539.317,
      457,
      341
    ],
    [
      1765057853576.319,
      470,
      324
    ],
    [
      1765057853613.1233,
      495,
      324
    ],
    [
      1765057853647.228,
      495,
      324
    ],
    [
      1765057853688.697,
      507,
      324
    ],
    [
      1765057853724.603,
      507,
      324
    ],
    [
      1765057853758.558,
      519,
      324
    ],
    [
      1765057853794.4429,
      569,
      357
    ],
    [
      1765057853830.7068,
      644,
      374
    ],
    [
      1765057853872.658,
      793,
      408
    ],
    [
      1765057853906.877,
      855,
      774
    ],
    [
      1765057853942.864,
      981,
      939
    ],
    [
      1765057853977.371,
      1119,
      939
    ],
    [
      1765057854013.582,
      1232,
      972
    ],
    [
      1765057854055.918,
      1296,
      981
    ],
    [
      1765057854092.016,
      1321,
      981
    ],
    [
      1765057854126.626,
      1321,
      981
    ],
    [
      1765057854167.4612,
      1423,
      873
    ],
    [
      1765057854203.9521,
      1511,
      658
    ],
    [
      1765057854237.629,
      1511,
      658
    ],
    [
      1765057854272.639,
      1511,
      641
    ],
    [
      1765057854309.324,
      1487,
      625
    ],
    [
      1765057854350.996,
      1461,
      608
    ],
    [
      1765057854391.2,
      1436,
      608
    ],
    [
      1765057854427.371,
      1410,
      591
    ],
    [
      1765057854461.468,
      1397,
      591
    ],
    [
      1765057854494.434,
      1385,
      575
    ],
    [
      1765057854536.5132,
      1385,
      575
    ],
    [
      1765057854572.4922,
      1385,
      575
    ],
    [
      1765057854606.2588,
      1385,
      575
    ],
    [
      1765057854647.1272,
      1385,
      575
    ],
    [
      1765057854689.9578,
      1385,
      575
    ],
    [
      1765057854733.9949,
      1385,
      575
    ],
    [
      1765057854767.597,
      1385,
      575
    ],
    [
      1765057854803.901,
      1372,
      575
    ],
    [
      1765057854843.901,
      1321,
      558
    ],
    [
      1765057854888.177,
      1220,
      525
    ],
    [
      1765057854923.61,
      1157,
      508
    ],
    [
      1765057854960.918,
      1006,
      475
    ],
    [
      1765057855001.4,
      868,
      458
    ],
    [
      1765057855038.392,
      706,
      408
    ],
    [
      1765057855072.646,
      619,
      408
    ],
    [
      1765057855109.4668,
      519,
      374
    ],
    [
      1765057855152.631,
      482,
      357
    ],
    [
      1765057855193.312,
      482,
      357
    ],
    [
      1765057855229.46,
      495,
      341
    ],
    [
      1765057855264.097,
      507,
      341
    ],
    [
      1765057855303.344,
      507,
      341
    ],
    [
      1765057855340.1743,
      507,
      341
    ],
    [
      1765057855374.322,
      507,
      341
    ],
    [
      1765057855410.924,
      482,
      691
    ],
    [
      1765057855450.8801,
      457,
      774
    ],
    [
      1765057855488.477,
      457,
      774
    ],
    [
      1765057855527.5881,
      457,
      774
    ],
    [
      1765057855563.88,
      457,
      774
    ],
    [
      1765057855598.269,
      457,
      774
    ],
    [
      1765057855631.7273,
      457,
      774
    ],
    [
      1765057855665.448,
      470,
      791
    ],
    [
      1765057855702.574,
      482,
      774
    ],
    [
      1765057855741.709,
      507,
      791
    ],
    [
      1765057855783.4292,
      781,
      824
    ],
    [
      1765057855818.439,
      868,
      840
    ],
    [
      1765057855852.457,
      968,
      857
    ],
    [
      1765057855888.205,
      1056,
      889
    ],
    [
      1765057855925.3198,
      1157,
      906
    ],
    [
      1765057855966.317,
      1220,
      922
    ],
    [
      1765057856001.101,
      1245,
      939
    ],
    [
      1765057856036.9978,
      1245,
      939
    ],
    [
      1765057856071.218,
      1182,
      658
    ],
    [
      1765057856107.668,
      1119,
      525
    ],
    [
      1765057856148.284,
      1106,
      508
    ],
    [
      1765057856183.26,
      1094,
      491
    ],
    [
      1765057856216.5762,
      1094,
      491
    ],
    [
      1765057856253.713,
      1081,
      491
    ],
    [
      1765057856293.66,
      1182,
      475
    ],
    [
      1765057856335.836,
      1169,
      475
    ],
    [
      1765057856371.257,
      1157,
      475
    ],
    [
      1765057856406.4683,
      1157,
      475
    ],
    [
      1765057856451.9,
      1157,
      475
    ],
    [
      1765057856487.9912,
      1157,
      475
    ],
    [
      1765057856531.172,
      1144,
      475
    ],
    [
      1765057856566.0042,
      1144,
      475
    ],
    [
      1765057856602.02,
      1144,
      475
    ],
    [
      1765057856635.9639,
      1144,
      475
    ],
    [
      1765057856668.8518,
      1131,
      458
    ],
    [
      1765057856704.154,
      1056,
      441
    ],
    [
      1765057856740.568,
      1056,
      441
    ],
    [
      1765057856775.517,
      1056,
      441
    ],
    [
      1765057856812.243,
      1069,
      441
    ],
    [
      1765057856845.366,
      1094,
      458
    ],
    [
      1765057856878.044,
      1131,
      475
    ],
    [
      1765057856921.675,
      1207,
      491
    ],
    [
      1765057856957.429,
      1296,
      508
    ],
    [
      1765057856989.995,
      1334,
      525
    ],
    [
      1765057857027.4802,
      1359,
      541
    ],
    [
      1765057857061.407,
      1359,
      541
    ],
    [
      1765057857095.708,
      1334,
      541
    ],
    [
      1765057857131.398,
      1283,
      525
    ],
    [
      1765057857166.857,
      1182,
      575
    ],
    [
      1765057857203.553,
      943,
      774
    ],
    [
      1765057857236.8782,
      843,
      758
    ],
    [
      1765057857271.914,
      731,
      741
    ],
    [
      1765057857305.887,
      606,
      724
    ],
    [
      1765057857340.321,
      495,
      708
    ],
    [
      1765057857382.611,
      272,
      675
    ],
    [
      1765057857425.687,
      185,
      675
    ],
    [
      1765057857461.038,
      148,
      658
    ],
    [
      1765057857496.021,
      123,
      658
    ],
    [
      1765057857532.711,
      111,
      641
    ],
    [
      1765057857566.0789,
      111,
      641
    ],
    [
      1765057857601.45,
      123,
      641
    ],
    [
      1765057857636.5068,
      136,
      641
    ],
    [
      1765057857671.233,
      136,
      641
    ],
    [
      1765057857706.4043,
      136,
      641
    ],
    [
      1765057857741.848,
      148,
      641
    ],
    [
      1765057857776.18,
      148,
      724
    ],
    [
      1765057857811.6438,
      148,
      741
    ],
    [
      1765057857845.9749,
      136,
      741
    ],
    [
      1765057857889.456,
      148,
      741
    ],
    [
      1765057857924.275,
      148,
      741
    ],
    [
      1765057857959.5679,
      148,
      724
    ],
    [
      1765057857996.5298,
      148,
      724
    ],
    [
      1765057858035.8022,
      160,
      724
    ],
    [
      1765057858069.279,
      185,
      724
    ],
    [
      1765057858112.723,
      470,
      724
    ],
    [
      1765057858154.562,
      470,
      724
    ],
    [
      1765057858189.9253,
      482,
      724
    ],
    [
      1765057858226.584,
      482,
      724
    ],
    [
      1765057858265.0981,
      495,
      724
    ],
    [
      1765057858301.1572,
      420,
      691
    ],
    [
      1765057858335.125,
      420,
      691
    ],
    [
      1765057858378.2458,
      420,
      691
    ],
    [
      1765057858412.217,
      433,
      691
    ],
    [
      1765057858453.8171,
      433,
      708
    ],
    [
      1765057858493.703,
      433,
      708
    ],
    [
      1765057858528.417,
      433,
      708
    ],
    [
      1765057858564.8582,
      445,
      708
    ],
    [
      1765057858607.208,
      445,
      724
    ],
    [
      1765057858643.3853,
      457,
      724
    ],
    [
      1765057858678.52,
      457,
      724
    ],
    [
      1765057858711.7498,
      457,
      807
    ],
    [
      1765057858747.966,
      457,
      840
    ],
    [
      1765057858782.7551,
      457,
      824
    ],
    [
      1765057858819.1218,
      445,
      824
    ],
    [
      1765057858853.781,
      445,
      824
    ],
    [
      1765057858889.521,
      210,
      541
    ],
    [
      1765057858936.6912,
      0,
      256
    ],
    [
      1765057858976.8,
      0,
      273
    ],
    [
      1765057859013.5369,
      0,
      273
    ],
    [
      1765057859047.9622,
      0,
      290
    ],
    [
      1765057859084.336,
      0,
      290
    ],
    [
      1765057859119.005,
      0,
      273
    ],
    [
      1765057859168.596,
      0,
      273
    ],
    [
      1765057859203.691,
      0,
      273
    ],
    [
      1765057859237.924,
      321,
      256
    ],
    [
      1765057859273.647,
      457,
      290
    ],
    [
      1765057859309.7659,
      457,
      290
    ],
    [
      1765057859349.977,
      457,
      290
    ],
    [
      1765057859385.6167,
      457,
      290
    ],
    [
      1765057859419.1401,
      457,
      290
    ],
    [
      1765057859453.336,
      470,
      290
    ],
    [
      1765057859488.2668,
      470,
      273
    ],
    [
      1765057859524.5178,
      532,
      189
    ],
    [
      1765057859559.663,
      1511,
      981
    ],
    [
      1765057859595.464,
      1511,
      981
    ],
    [
      1765057859635.571,
      843,
      256
    ],
    [
      1765057859671.371,
      868,
      172
    ],
    [
      1765057859707.4348,
      868,
      206
    ],
    [
      1765057859742.849,
      868,
      206
    ],
    [
      1765057859784.6838,
      868,
      223
    ],
    [
      1765057859827.268,
      880,
      223
    ],
    [
      1765057859860.051,
      880,
      223
    ],
    [
      1765057859896.5781,
      931,
      273
    ],
    [
      1765057859933.2402,
      931,
      290
    ],
    [
      1765057859968.0588,
      931,
      307
    ],
    [
      1765057860004.569,
      931,
      307
    ],
    [
      1765057860039.368,
      931,
      307
    ],
    [
      1765057860073.864,
      931,
      307
    ],
    [
      1765057860108.59,
      931,
      290
    ],
    [
      1765057860150.709,
      943,
      290
    ],
    [
      1765057860192.5718,
      943,
      307
    ],
    [
      1765057860227.886,
      943,
      290
    ],
    [
      1765057860261.218,
      943,
      307
    ],
    [
      1765057860310.457,
      793,
      508
    ],
    [
      1765057860343.8552,
      619,
      807
    ],
    [
      1765057860385.567,
      606,
      807
    ],
    [
      1765057860421.25,
      606,
      807
    ],
    [
      1765057860455.2478,
      606,
      807
    ],
    [
      1765057860492.2021,
      606,
      807
    ],
    [
      1765057860532.9822,
      606,
      807
    ],
    [
      1765057860574.6792,
      606,
      807
    ],
    [
      1765057860614.979,
      606,
      807
    ],
    [
      1765057860653.4788,
      606,
      824
    ],
    [
      1765057860707.644,
      606,
      807
    ],
    [
      1765057860745.452,
      606,
      807
    ],
    [
      1765057860786.229,
      606,
      807
    ],
    [
      1765057860823.946,
      606,
      807
    ],
    [
      1765057860862.901,
      669,
      774
    ],
    [
      1765057860897.6719,
      706,
      774
    ],
    [
      1765057860933.9788,
      706,
      758
    ],
    [
      1765057860971.118,
      706,
      758
    ],
    [
      1765057861007.0989,
      681,
      658
    ],
    [
      1765057861049.0369,
      644,
      121
    ],
    [
      1765057861104.007,
      631,
      155
    ],
    [
      1765057861142.762,
      631,
      138
    ],
    [
      1765057861185.729,
      631,
      138
    ],
    [
      1765057861233.79,
      631,
      138
    ],
    [
      1765057861268.6912,
      631,
      138
    ],
    [
      1765057861304.467,
      644,
      138
    ],
    [
      1765057861340.992,
      644,
      138
    ],
    [
      1765057861383.298,
      644,
      138
    ],
    [
      1765057861424.9758,
      644,
      138
    ],
    [
      1765057861466.002,
      644,
      138
    ],
    [
      1765057861501.198,
      656,
      172
    ],
    [
      1765057861537.236,
      569,
      873
    ],
    [
      1765057861573.824,
      507,
      981
    ],
    [
      1765057861606.587,
      495,
      981
    ],
    [
      1765057861640.801,
      495,
      981
    ],
    [
      1765057861678.6492,
      495,
      981
    ],
    [
      1765057861718.314,
      495,
      981
    ],
    [
      1765057861761.135,
      507,
      981
    ],
    [
      1765057861797.3481,
      519,
      981
    ],
    [
      1765057861839.529,
      532,
      922
    ],
    [
      1765057861876.19,
      619,
      374
    ],
    [
      1765057861916.9368,
      594,
      374
    ],
    [
      1765057861959.897,
      594,
      374
    ],
    [
      1765057861995.7349,
      594,
      374
    ],
    [
      1765057862031.104,
      606,
      357
    ],
    [
      1765057862066.409,
      718,
      981
    ],
    [
      1765057862100.495,
      693,
      981
    ],
    [
      1765057862134.504,
      693,
      981
    ],
    [
      1765057862168.353,
      681,
      981
    ],
    [
      1765057862207.5132,
      693,
      981
    ],
    [
      1765057862245.1992,
      743,
      981
    ],
    [
      1765057862279.5679,
      743,
      981
    ],
    [
      1765057862314.6018,
      756,
      981
    ],
    [
      1765057862350.0469,
      756,
      981
    ],
    [
      1765057862382.657,
      756,
      981
    ],
    [
      1765057862416.7512,
      756,
      981
    ],
    [
      1765057862452.481,
      756,
      981
    ],
    [
      1765057862495.589,
      806,
      508
    ],
    [
      1765057862538.008,
      768,
      525
    ],
    [
      1765057862573.6057,
      768,
      525
    ],
    [
      1765057862614.5378,
      756,
      525
    ],
    [
      1765057862648.375,
      756,
      525
    ],
    [
      1765057862684.8098,
      756,
      525
    ],
    [
      1765057862718.694,
      756,
      525
    ],
    [
      1765057862760.961,
      756,
      508
    ],
    [
      1765057862796.0151,
      743,
      625
    ],
    [
      1765057862835.885,
      731,
      774
    ],
    [
      1765057862870.882,
      718,
      774
    ],
    [
      1765057862912.0012,
      718,
      774
    ],
    [
      1765057862945.911,
      718,
      774
    ],
    [
      1765057862982.817,
      706,
      774
    ],
    [
      1765057863018.971,
      706,
      791
    ],
    [
      1765057863065.382,
      706,
      774
    ],
    [
      1765057863100.1711,
      706,
      791
    ],
    [
      1765057863137.022,
      706,
      774
    ],
    [
      1765057863172.655,
      706,
      774
    ],
    [
      1765057863208.7412,
      855,
      155
    ],
    [
      1765057863245.159,
      843,
      189
    ],
    [
      1765057863285.207,
      843,
      189
    ],
    [
      1765057863319.613,
      831,
      189
    ],
    [
      1765057863362.5789,
      831,
      172
    ],
    [
      1765057863398.143,
      831,
      172
    ],
    [
      1765057863432.368,
      818,
      172
    ],
    [
      1765057863468.103,
      284,
      54
    ],
    [
      1765057863500.632,
      259,
      54
    ],
    [
      1765057863534.3699,
      247,
      37
    ],
    [
      1765057863570.788,
      247,
      37
    ],
    [
      1765057863605.299,
      247,
      37
    ],
    [
      1765057863648.386,
      235,
      37
    ],
    [
      1765057863684.0872,
      247,
      54
    ],
    [
      1765057863717.8318,
      247,
      37
    ],
    [
      1765057863752.278,
      247,
      37
    ],
    [
      1765057863787.3699,
      284,
      138
    ],
    [
      1765057863822.7961,
      296,
      223
    ],
    [
      1765057863859.437,
      284,
      223
    ],
    [
      1765057863893.771,
      284,
      223
    ],
    [
      1765057863928.0332,
      284,
      223
    ],
    [
      1765057863976.6929,
      818,
      458
    ],
    [
      1765057864010.457,
      806,
      441
    ],
    [
      1765057864044.464,
      793,
      441
    ],
    [
      1765057864079.749,
      793,
      441
    ],
    [
      1765057864120.4888,
      781,
      441
    ],
    [
      1765057864156.4338,
      781,
      441
    ],
    [
      1765057864192.7192,
      656,
      641
    ],
    [
      1765057864226.477,
      619,
      675
    ],
    [
      1765057864262.023,
      619,
      675
    ],
    [
      1765057864304.624,
      606,
      675
    ],
    [
      1765057864340.31,
      606,
      658
    ],
    [
      1765057864374.783,
      606,
      675
    ],
    [
      1765057864411.135,
      718,
      121
    ],
    [
      1765057864449.9058,
      706,
      138
    ],
    [
      1765057864485.898,
      693,
      138
    ],
    [
      1765057864528.8582,
      693,
      138
    ],
    [
      1765057864566.1418,
      693,
      121
    ],
    [
      1765057864600.53,
      693,
      121
    ],
    [
      1765057864636.928,
      681,
      121
    ],
    [
      1765057864670.405,
      681,
      121
    ],
    [
      1765057864713.802,
      669,
      121
    ],
    [
      1765057864747.7961,
      582,
      172
    ],
    [
      1765057864782.873,
      569,
      172
    ],
    [
      1765057864817.3928,
      569,
      172
    ],
    [
      1765057864853.604,
      569,
      172
    ],
    [
      1765057864894.456,
      569,
      172
    ],
    [
      1765057864931.469,
      557,
      155
    ],
    [
      1765057864968.3171,
      557,
      172
    ],
    [
      1765057865005.2869,
      793,
      458
    ],
    [
      1765057865040.253,
      781,
      458
    ],
    [
      1765057865077.962,
      768,
      441
    ],
    [
      1765057865118.491,
      768,
      441
    ],
    [
      1765057865152.729,
      756,
      441
    ],
    [
      1765057865189.928,
      756,
      441
    ],
    [
      1765057865223.71,
      743,
      424
    ],
    [
      1765057865266.439,
      743,
      424
    ],
    [
      1765057865302.123,
      743,
      424
    ],
    [
      1765057865336.884,
      743,
      424
    ],
    [
      1765057865372.2788,
      731,
      424
    ],
    [
      1765057865407.4768,
      731,
      424
    ],
    [
      1765057865449.365,
      706,
      475
    ],
    [
      1765057865483.6008,
      557,
      708
    ],
    [
      1765057865519.3533,
      557,
      708
    ],
    [
      1765057865560.063,
      544,
      708
    ],
    [
      1765057865599.498,
      544,
      708
    ],
    [
      1765057865635.1309,
      569,
      675
    ],
    [
      1765057865669.525,
      594,
      675
    ],
    [
      1765057865705.065,
      594,
      675
    ],
    [
      1765057865748.228,
      594,
      675
    ],
    [
      1765057865784.3132,
      606,
      675
    ],
    [
      1765057865818.059,
      606,
      675
    ],
    [
      1765057865859.045,
      594,
      658
    ],
    [
      1765057865894.7808,
      594,
      658
    ],
    [
      1765057865927.7297,
      594,
      658
    ],
    [
      1765057865964.968,
      594,
      658
    ],
    [
      1765057865998.968,
      606,
      658
    ],
    [
      1765057866032.105,
      631,
      658
    ],
    [
      1765057866068.1128,
      781,
      708
    ],
    [
      1765057866101.976,
      768,
      708
    ],
    [
      1765057866135.2,
      768,
      691
    ],
    [
      1765057866178.209,
      768,
      691
    ],
    [
      1765057866213.4158,
      756,
      708
    ],
    [
      1765057866249.398,
      731,
      708
    ],
    [
      1765057866289.602,
      731,
      708
    ],
    [
      1765057866325.762,
      731,
      708
    ],
    [
      1765057866360.372,
      731,
      691
    ],
    [
      1765057866403.021,
      731,
      708
    ],
    [
      1765057866438.34,
      718,
      691
    ],
    [
      1765057866473.349,
      718,
      691
    ],
    [
      1765057866506.086,
      718,
      691
    ],
    [
      1765057866543.309,
      706,
      691
    ]
  ]
}